{
  "date": "2026-06-26",
  "externalFeedsUpdatedAt": "2026-06-26T13:04:04.811214Z",
  "external_feeds": {
    "scores24_fifa_world_cup": {
      "date": "2026-06-26",
      "generatedAt": "2026-06-26T13:04:04.811214Z",
      "generatedBy": "github-actions:external-feed-refresh",
      "meta": {
        "attemptedUrls": 6,
        "blockRetryRounds": 0,
        "blockedUrls": 0,
        "date": "2026-06-26",
        "expectedMatchups": 6,
        "feed": "scores24_fifa_world_cup",
        "from": "github-actions",
        "leagues": "mlb,wnba,fifa_world_cup",
        "listingLinks": 12,
        "matchedPicks": 6,
        "missingMatchups": [],
        "officialMatchups": 6,
        "unpublishedMatchups": [],
        "updatedAt": "2026-06-26T13:04:04.811214Z"
      },
      "note": "Scores24FIFAWorldCup matched 6 published editorial choice(s) against 6 official 2026-06-26 matchup(s).",
      "ok": true,
      "picks": [
        {
          "away_team": "France",
          "calibration_excluded": true,
          "date": "2026-06-26",
          "decision": "BET",
          "edge": null,
          "game": "France @ Norway",
          "grade_supported": false,
          "home_team": "Norway",
          "market_type": "soccer_specialty",
          "matchup": "France @ Norway",
          "odds": -152,
          "pick": "Both Teams To Score (Yes) (France @ Norway)",
          "probability": null,
          "source": "Scores24FIFAWorldCup",
          "source_url": "https://scores24.live/en/soccer/m-27-06-2026-norway-france-prediction",
          "sport": "FIFA WC",
          "start_time": "2026-06-26T19:00Z",
          "tip": "Both Teams To Score (Yes)",
          "units": 1
        },
        {
          "away_team": "Iraq",
          "calibration_excluded": true,
          "date": "2026-06-26",
          "decision": "BET",
          "edge": null,
          "game": "Iraq @ Senegal",
          "grade_supported": false,
          "home_team": "Senegal",
          "market_type": "soccer_specialty",
          "matchup": "Iraq @ Senegal",
          "odds": -152,
          "pick": "Senegal Handicap (-1,5) (Iraq @ Senegal)",
          "probability": null,
          "source": "Scores24FIFAWorldCup",
          "source_url": "https://scores24.live/en/soccer/m-26-06-2026-senegal-iraq-prediction",
          "sport": "FIFA WC",
          "start_time": "2026-06-26T19:00Z",
          "tip": "Senegal Handicap (-1,5)",
          "units": 1
        },
        {
          "away_team": "Saudi Arabia",
          "calibration_excluded": true,
          "date": "2026-06-26",
          "decision": "BET",
          "edge": null,
          "game": "Saudi Arabia @ Cape Verde",
          "grade_supported": false,
          "home_team": "Cape Verde",
          "market_type": "soccer_specialty",
          "matchup": "Saudi Arabia @ Cape Verde",
          "odds": -175,
          "pick": "Cape Verde Total goals Over (1) (Saudi Arabia @ Cape Verde)",
          "probability": null,
          "source": "Scores24FIFAWorldCup",
          "source_url": "https://scores24.live/en/soccer/m-27-06-2026-cape-verde-saudi-arabia-prediction",
          "sport": "FIFA WC",
          "start_time": "2026-06-27T00:00Z",
          "tip": "Cape Verde Total goals Over (1)",
          "units": 1
        },
        {
          "away_team": "Spain",
          "calibration_excluded": true,
          "date": "2026-06-26",
          "decision": "BET",
          "edge": null,
          "game": "Spain @ Uruguay",
          "grade_supported": false,
          "home_team": "Uruguay",
          "market_type": "soccer_specialty",
          "matchup": "Spain @ Uruguay",
          "odds": -108,
          "pick": "Both Teams To Score (Yes) (Spain @ Uruguay)",
          "probability": null,
          "source": "Scores24FIFAWorldCup",
          "source_url": "https://scores24.live/en/soccer/m-27-06-2026-uruguay-spain-prediction",
          "sport": "FIFA WC",
          "start_time": "2026-06-27T00:00Z",
          "tip": "Both Teams To Score (Yes)",
          "units": 1
        },
        {
          "away_team": "Iran",
          "calibration_excluded": true,
          "date": "2026-06-26",
          "decision": "BET",
          "edge": null,
          "game": "Iran @ Egypt",
          "grade_supported": false,
          "home_team": "Egypt",
          "market_type": "soccer_specialty",
          "matchup": "Iran @ Egypt",
          "odds": -175,
          "pick": "Egypt 0 (Iran @ Egypt)",
          "probability": null,
          "source": "Scores24FIFAWorldCup",
          "source_url": "https://scores24.live/en/soccer/m-27-06-2026-egypt-iran-prediction",
          "sport": "FIFA WC",
          "start_time": "2026-06-27T03:00Z",
          "tip": "Egypt Handicap (0)",
          "units": 1
        },
        {
          "away_team": "Belgium",
          "calibration_excluded": true,
          "date": "2026-06-26",
          "decision": "BET",
          "edge": null,
          "game": "Belgium @ New Zealand",
          "grade_supported": false,
          "home_team": "New Zealand",
          "market_type": "soccer_specialty",
          "matchup": "Belgium @ New Zealand",
          "odds": 129,
          "pick": "Both Teams To Score (Yes) (Belgium @ New Zealand)",
          "probability": null,
          "source": "Scores24FIFAWorldCup",
          "source_url": "https://scores24.live/en/soccer/m-27-06-2026-new-zealand-belgium-prediction",
          "sport": "FIFA WC",
          "start_time": "2026-06-27T03:00Z",
          "tip": "Both Teams To Score (Yes)",
          "units": 1
        }
      ],
      "updatedAt": "2026-06-26T13:04:04.811214Z"
    },
    "scores24_mlb": {
      "date": "2026-06-26",
      "generatedAt": "2026-06-26T13:04:04.811214Z",
      "generatedBy": "github-actions:external-feed-refresh",
      "meta": {
        "attemptedUrls": 20,
        "blockRetryRounds": 0,
        "blockedUrls": 0,
        "date": "2026-06-26",
        "expectedMatchups": 14,
        "feed": "scores24_mlb",
        "from": "github-actions",
        "leagues": "mlb,wnba,fifa_world_cup",
        "listingLinks": 12,
        "matchedPicks": 14,
        "missingMatchups": [],
        "officialMatchups": 15,
        "unpublishedMatchups": [
          "Atlanta Braves @ San Francisco Giants"
        ],
        "updatedAt": "2026-06-26T13:04:04.811214Z"
      },
      "note": "Scores24MLB matched 14 published editorial choice(s) against 15 official 2026-06-26 matchup(s).",
      "ok": true,
      "picks": [
        {
          "away_team": "Cincinnati Reds",
          "date": "2026-06-26",
          "decision": "BET",
          "edge": null,
          "game": "Cincinnati Reds @ Pittsburgh Pirates",
          "home_team": "Pittsburgh Pirates",
          "matchup": "Cincinnati Reds @ Pittsburgh Pirates",
          "odds": -217,
          "pick": "Pittsburgh Pirates ML (Cincinnati Reds @ Pittsburgh Pirates)",
          "pregame_snapshot": {
            "away_team": "Cincinnati Reds",
            "date": "2026-06-26",
            "decision": "BET",
            "edge": null,
            "game": "Cincinnati Reds @ Pittsburgh Pirates",
            "home_team": "Pittsburgh Pirates",
            "matchup": "Cincinnati Reds @ Pittsburgh Pirates",
            "odds": -217,
            "pick": "Pittsburgh Pirates ML (Cincinnati Reds @ Pittsburgh Pirates)",
            "probability": null,
            "source": "Scores24MLB",
            "source_url": "https://scores24.live/en/baseball/m-26-06-2026-pittsburgh-pirates-cincinnati-reds-prediction",
            "sport": "MLB",
            "start_time": "2026-06-26T22:40Z",
            "tip": "Pittsburgh Pirates Win",
            "units": 1
          },
          "probability": null,
          "source": "Scores24MLB",
          "source_url": "https://scores24.live/en/baseball/m-26-06-2026-pittsburgh-pirates-cincinnati-reds-prediction",
          "sport": "MLB",
          "start_time": "2026-06-26T22:40Z",
          "tip": "Pittsburgh Pirates Win",
          "units": 1
        },
        {
          "away_team": "Houston Astros",
          "date": "2026-06-26",
          "decision": "BET",
          "edge": null,
          "game": "Houston Astros @ Detroit Tigers",
          "home_team": "Detroit Tigers",
          "matchup": "Houston Astros @ Detroit Tigers",
          "odds": -189,
          "pick": "Total Under (9,5) (Houston Astros @ Detroit Tigers)",
          "pregame_snapshot": {
            "away_team": "Houston Astros",
            "date": "2026-06-26",
            "decision": "BET",
            "edge": null,
            "game": "Houston Astros @ Detroit Tigers",
            "home_team": "Detroit Tigers",
            "matchup": "Houston Astros @ Detroit Tigers",
            "odds": -189,
            "pick": "Total Under (9,5) (Houston Astros @ Detroit Tigers)",
            "probability": null,
            "source": "Scores24MLB",
            "source_url": "https://scores24.live/en/baseball/m-26-06-2026-detroit-tigers-houston-astros-prediction",
            "sport": "MLB",
            "start_time": "2026-06-26T22:40Z",
            "tip": "Total Under (9,5)",
            "units": 1
          },
          "probability": null,
          "source": "Scores24MLB",
          "source_url": "https://scores24.live/en/baseball/m-26-06-2026-detroit-tigers-houston-astros-prediction",
          "sport": "MLB",
          "start_time": "2026-06-26T22:40Z",
          "tip": "Total Under (9,5)",
          "units": 1
        },
        {
          "away_team": "Washington Nationals",
          "date": "2026-06-26",
          "decision": "BET",
          "edge": null,
          "game": "Washington Nationals @ Baltimore Orioles",
          "home_team": "Baltimore Orioles",
          "matchup": "Washington Nationals @ Baltimore Orioles",
          "odds": -152,
          "pick": "Total Under (9,5) (Washington Nationals @ Baltimore Orioles)",
          "pregame_snapshot": {
            "away_team": "Washington Nationals",
            "date": "2026-06-26",
            "decision": "BET",
            "edge": null,
            "game": "Washington Nationals @ Baltimore Orioles",
            "home_team": "Baltimore Orioles",
            "matchup": "Washington Nationals @ Baltimore Orioles",
            "odds": -152,
            "pick": "Total Under (9,5) (Washington Nationals @ Baltimore Orioles)",
            "probability": null,
            "source": "Scores24MLB",
            "source_url": "https://scores24.live/en/baseball/m-26-06-2026-baltimore-orioles-washington-nationals-prediction",
            "sport": "MLB",
            "start_time": "2026-06-26T23:05Z",
            "tip": "Total Under (9,5)",
            "units": 1
          },
          "probability": null,
          "source": "Scores24MLB",
          "source_url": "https://scores24.live/en/baseball/m-26-06-2026-baltimore-orioles-washington-nationals-prediction",
          "sport": "MLB",
          "start_time": "2026-06-26T23:05Z",
          "tip": "Total Under (9,5)",
          "units": 1
        },
        {
          "away_team": "Texas Rangers",
          "date": "2026-06-26",
          "decision": "BET",
          "edge": null,
          "game": "Texas Rangers @ Toronto Blue Jays",
          "home_team": "Toronto Blue Jays",
          "matchup": "Texas Rangers @ Toronto Blue Jays",
          "odds": -145,
          "pick": "Toronto Blue Jays Total Over (3,5) (Texas Rangers @ Toronto Blue Jays)",
          "pregame_snapshot": {
            "away_team": "Texas Rangers",
            "date": "2026-06-26",
            "decision": "BET",
            "edge": null,
            "game": "Texas Rangers @ Toronto Blue Jays",
            "home_team": "Toronto Blue Jays",
            "matchup": "Texas Rangers @ Toronto Blue Jays",
            "odds": -145,
            "pick": "Toronto Blue Jays Total Over (3,5) (Texas Rangers @ Toronto Blue Jays)",
            "probability": null,
            "source": "Scores24MLB",
            "source_url": "https://scores24.live/en/baseball/m-26-06-2026-toronto-blue-jays-texas-rangers-prediction",
            "sport": "MLB",
            "start_time": "2026-06-26T23:07Z",
            "tip": "Toronto Blue Jays Total Over (3,5)",
            "units": 1
          },
          "probability": null,
          "source": "Scores24MLB",
          "source_url": "https://scores24.live/en/baseball/m-26-06-2026-toronto-blue-jays-texas-rangers-prediction",
          "sport": "MLB",
          "start_time": "2026-06-26T23:07Z",
          "tip": "Toronto Blue Jays Total Over (3,5)",
          "units": 1
        },
        {
          "away_team": "Arizona Diamondbacks",
          "date": "2026-06-26",
          "decision": "BET",
          "edge": null,
          "game": "Arizona Diamondbacks @ Tampa Bay Rays",
          "home_team": "Tampa Bay Rays",
          "matchup": "Arizona Diamondbacks @ Tampa Bay Rays",
          "odds": -141,
          "pick": "Tampa Bay Rays ML (Arizona Diamondbacks @ Tampa Bay Rays)",
          "pregame_snapshot": {
            "away_team": "Arizona Diamondbacks",
            "date": "2026-06-26",
            "decision": "BET",
            "edge": null,
            "game": "Arizona Diamondbacks @ Tampa Bay Rays",
            "home_team": "Tampa Bay Rays",
            "matchup": "Arizona Diamondbacks @ Tampa Bay Rays",
            "odds": -141,
            "pick": "Tampa Bay Rays ML (Arizona Diamondbacks @ Tampa Bay Rays)",
            "probability": null,
            "source": "Scores24MLB",
            "source_url": "https://scores24.live/en/baseball/m-26-06-2026-tampa-bay-rays-arizona-diamondbacks-prediction",
            "sport": "MLB",
            "start_time": "2026-06-26T23:10Z",
            "tip": "Tampa Bay Rays Win",
            "units": 1
          },
          "probability": null,
          "source": "Scores24MLB",
          "source_url": "https://scores24.live/en/baseball/m-26-06-2026-tampa-bay-rays-arizona-diamondbacks-prediction",
          "sport": "MLB",
          "start_time": "2026-06-26T23:10Z",
          "tip": "Tampa Bay Rays Win",
          "units": 1
        },
        {
          "away_team": "New York Yankees",
          "date": "2026-06-26",
          "decision": "BET",
          "edge": null,
          "game": "New York Yankees @ Boston Red Sox",
          "home_team": "Boston Red Sox",
          "matchup": "New York Yankees @ Boston Red Sox",
          "odds": -161,
          "pick": "Total Under (9,5) (New York Yankees @ Boston Red Sox)",
          "pregame_snapshot": {
            "away_team": "New York Yankees",
            "date": "2026-06-26",
            "decision": "BET",
            "edge": null,
            "game": "New York Yankees @ Boston Red Sox",
            "home_team": "Boston Red Sox",
            "matchup": "New York Yankees @ Boston Red Sox",
            "odds": -161,
            "pick": "Total Under (9,5) (New York Yankees @ Boston Red Sox)",
            "probability": null,
            "source": "Scores24MLB",
            "source_url": "https://scores24.live/en/baseball/m-26-06-2026-boston-red-sox-new-york-yankees-prediction",
            "sport": "MLB",
            "start_time": "2026-06-26T23:10Z",
            "tip": "Total Under (9,5)",
            "units": 1
          },
          "probability": null,
          "source": "Scores24MLB",
          "source_url": "https://scores24.live/en/baseball/m-26-06-2026-boston-red-sox-new-york-yankees-prediction",
          "sport": "MLB",
          "start_time": "2026-06-26T23:10Z",
          "tip": "Total Under (9,5)",
          "units": 1
        },
        {
          "away_team": "Philadelphia Phillies",
          "date": "2026-06-26",
          "decision": "BET",
          "edge": null,
          "game": "Philadelphia Phillies @ New York Mets",
          "home_team": "New York Mets",
          "matchup": "Philadelphia Phillies @ New York Mets",
          "odds": -159,
          "pick": "Philadelphia Phillies ML (Philadelphia Phillies @ New York Mets)",
          "pregame_snapshot": {
            "away_team": "Philadelphia Phillies",
            "date": "2026-06-26",
            "decision": "BET",
            "edge": null,
            "game": "Philadelphia Phillies @ New York Mets",
            "home_team": "New York Mets",
            "matchup": "Philadelphia Phillies @ New York Mets",
            "odds": -159,
            "pick": "Philadelphia Phillies ML (Philadelphia Phillies @ New York Mets)",
            "probability": null,
            "source": "Scores24MLB",
            "source_url": "https://scores24.live/en/baseball/m-26-06-2026-new-york-mets-philadelphia-phillies-prediction",
            "sport": "MLB",
            "start_time": "2026-06-26T23:10Z",
            "tip": "Philadelphia Phillies Win",
            "units": 1
          },
          "probability": null,
          "source": "Scores24MLB",
          "source_url": "https://scores24.live/en/baseball/m-26-06-2026-new-york-mets-philadelphia-phillies-prediction",
          "sport": "MLB",
          "start_time": "2026-06-26T23:10Z",
          "tip": "Philadelphia Phillies Win",
          "units": 1
        },
        {
          "away_team": "Seattle Mariners",
          "date": "2026-06-26",
          "decision": "BET",
          "edge": null,
          "game": "Seattle Mariners @ Cleveland Guardians",
          "home_team": "Cleveland Guardians",
          "matchup": "Seattle Mariners @ Cleveland Guardians",
          "odds": -112,
          "pick": "Cleveland Gardians ML (Seattle Mariners @ Cleveland Guardians)",
          "pregame_snapshot": {
            "away_team": "Seattle Mariners",
            "date": "2026-06-26",
            "decision": "BET",
            "edge": null,
            "game": "Seattle Mariners @ Cleveland Guardians",
            "home_team": "Cleveland Guardians",
            "matchup": "Seattle Mariners @ Cleveland Guardians",
            "odds": -112,
            "pick": "Cleveland Gardians ML (Seattle Mariners @ Cleveland Guardians)",
            "probability": null,
            "source": "Scores24MLB",
            "source_url": "https://scores24.live/en/baseball/m-26-06-2026-cleveland-guardians-seattle-mariners-prediction",
            "sport": "MLB",
            "start_time": "2026-06-26T23:10Z",
            "tip": "Cleveland Gardians Win",
            "units": 1
          },
          "probability": null,
          "source": "Scores24MLB",
          "source_url": "https://scores24.live/en/baseball/m-26-06-2026-cleveland-guardians-seattle-mariners-prediction",
          "sport": "MLB",
          "start_time": "2026-06-26T23:10Z",
          "tip": "Cleveland Gardians Win",
          "units": 1
        },
        {
          "away_team": "Kansas City Royals",
          "date": "2026-06-26",
          "decision": "BET",
          "edge": null,
          "game": "Kansas City Royals @ Chicago White Sox",
          "home_team": "Chicago White Sox",
          "matchup": "Kansas City Royals @ Chicago White Sox",
          "odds": -137,
          "pick": "Total Over (7,5) (Kansas City Royals @ Chicago White Sox)",
          "pregame_snapshot": {
            "away_team": "Kansas City Royals",
            "date": "2026-06-26",
            "decision": "BET",
            "edge": null,
            "game": "Kansas City Royals @ Chicago White Sox",
            "home_team": "Chicago White Sox",
            "matchup": "Kansas City Royals @ Chicago White Sox",
            "odds": -137,
            "pick": "Total Over (7,5) (Kansas City Royals @ Chicago White Sox)",
            "probability": null,
            "source": "Scores24MLB",
            "source_url": "https://scores24.live/en/baseball/m-26-06-2026-chicago-white-sox-kansas-city-royals-prediction",
            "sport": "MLB",
            "start_time": "2026-06-26T23:40Z",
            "tip": "Total Over (7,5)",
            "units": 1
          },
          "probability": null,
          "source": "Scores24MLB",
          "source_url": "https://scores24.live/en/baseball/m-26-06-2026-chicago-white-sox-kansas-city-royals-prediction",
          "sport": "MLB",
          "start_time": "2026-06-26T23:40Z",
          "tip": "Total Over (7,5)",
          "units": 1
        },
        {
          "away_team": "Chicago Cubs",
          "date": "2026-06-26",
          "decision": "BET",
          "edge": null,
          "game": "Chicago Cubs @ Milwaukee Brewers",
          "home_team": "Milwaukee Brewers",
          "matchup": "Chicago Cubs @ Milwaukee Brewers",
          "odds": -189,
          "pick": "Total Over (6,5) (Chicago Cubs @ Milwaukee Brewers)",
          "pregame_snapshot": {
            "away_team": "Chicago Cubs",
            "date": "2026-06-26",
            "decision": "BET",
            "edge": null,
            "game": "Chicago Cubs @ Milwaukee Brewers",
            "home_team": "Milwaukee Brewers",
            "matchup": "Chicago Cubs @ Milwaukee Brewers",
            "odds": -189,
            "pick": "Total Over (6,5) (Chicago Cubs @ Milwaukee Brewers)",
            "probability": null,
            "source": "Scores24MLB",
            "source_url": "https://scores24.live/en/baseball/m-26-06-2026-milwaukee-brewers-chicago-cubs-prediction",
            "sport": "MLB",
            "start_time": "2026-06-26T23:45Z",
            "tip": "Total Over (6,5)",
            "units": 1
          },
          "probability": null,
          "source": "Scores24MLB",
          "source_url": "https://scores24.live/en/baseball/m-26-06-2026-milwaukee-brewers-chicago-cubs-prediction",
          "sport": "MLB",
          "start_time": "2026-06-26T23:45Z",
          "tip": "Total Over (6,5)",
          "units": 1
        },
        {
          "away_team": "Colorado Rockies",
          "date": "2026-06-26",
          "decision": "BET",
          "edge": null,
          "game": "Colorado Rockies @ Minnesota Twins",
          "home_team": "Minnesota Twins",
          "matchup": "Colorado Rockies @ Minnesota Twins",
          "odds": -141,
          "pick": "Total Over (8,5) (Colorado Rockies @ Minnesota Twins)",
          "pregame_snapshot": {
            "away_team": "Colorado Rockies",
            "date": "2026-06-26",
            "decision": "BET",
            "edge": null,
            "game": "Colorado Rockies @ Minnesota Twins",
            "home_team": "Minnesota Twins",
            "matchup": "Colorado Rockies @ Minnesota Twins",
            "odds": -141,
            "pick": "Total Over (8,5) (Colorado Rockies @ Minnesota Twins)",
            "probability": null,
            "source": "Scores24MLB",
            "source_url": "https://scores24.live/en/baseball/m-26-06-2026-minnesota-twins-colorado-rockies-prediction",
            "sport": "MLB",
            "start_time": "2026-06-27T00:10Z",
            "tip": "Total Over (8,5)",
            "units": 1
          },
          "probability": null,
          "source": "Scores24MLB",
          "source_url": "https://scores24.live/en/baseball/m-26-06-2026-minnesota-twins-colorado-rockies-prediction",
          "sport": "MLB",
          "start_time": "2026-06-27T00:10Z",
          "tip": "Total Over (8,5)",
          "units": 1
        },
        {
          "away_team": "Miami Marlins",
          "date": "2026-06-26",
          "decision": "BET",
          "edge": null,
          "game": "Miami Marlins @ St. Louis Cardinals",
          "home_team": "St. Louis Cardinals",
          "matchup": "Miami Marlins @ St. Louis Cardinals",
          "odds": 100,
          "pick": "Miami Marlins ML (Miami Marlins @ St. Louis Cardinals)",
          "pregame_snapshot": {
            "away_team": "Miami Marlins",
            "date": "2026-06-26",
            "decision": "BET",
            "edge": null,
            "game": "Miami Marlins @ St. Louis Cardinals",
            "home_team": "St. Louis Cardinals",
            "matchup": "Miami Marlins @ St. Louis Cardinals",
            "odds": 100,
            "pick": "Miami Marlins ML (Miami Marlins @ St. Louis Cardinals)",
            "probability": null,
            "source": "Scores24MLB",
            "source_url": "https://scores24.live/en/baseball/m-26-06-2026-st-louis-cardinals-miami-marlins-prediction",
            "sport": "MLB",
            "start_time": "2026-06-27T00:15Z",
            "tip": "Miami Marlins Win",
            "units": 1
          },
          "probability": null,
          "source": "Scores24MLB",
          "source_url": "https://scores24.live/en/baseball/m-26-06-2026-st-louis-cardinals-miami-marlins-prediction",
          "sport": "MLB",
          "start_time": "2026-06-27T00:15Z",
          "tip": "Miami Marlins Win",
          "units": 1
        },
        {
          "away_team": "Athletics",
          "date": "2026-06-26",
          "decision": "BET",
          "edge": null,
          "game": "Athletics @ Los Angeles Angels",
          "home_team": "Los Angeles Angels",
          "matchup": "Athletics @ Los Angeles Angels",
          "odds": -167,
          "pick": "Total Under (9,5) (Athletics @ Los Angeles Angels)",
          "pregame_snapshot": {
            "away_team": "Athletics",
            "date": "2026-06-26",
            "decision": "BET",
            "edge": null,
            "game": "Athletics @ Los Angeles Angels",
            "home_team": "Los Angeles Angels",
            "matchup": "Athletics @ Los Angeles Angels",
            "odds": -167,
            "pick": "Total Under (9,5) (Athletics @ Los Angeles Angels)",
            "probability": null,
            "source": "Scores24MLB",
            "source_url": "https://scores24.live/en/baseball/m-26-06-2026-los-angeles-angels-athletics-prediction",
            "sport": "MLB",
            "start_time": "2026-06-27T01:38Z",
            "tip": "Total Under (9,5)",
            "units": 1
          },
          "probability": null,
          "source": "Scores24MLB",
          "source_url": "https://scores24.live/en/baseball/m-26-06-2026-los-angeles-angels-athletics-prediction",
          "sport": "MLB",
          "start_time": "2026-06-27T01:38Z",
          "tip": "Total Under (9,5)",
          "units": 1
        },
        {
          "away_team": "Los Angeles Dodgers",
          "date": "2026-06-26",
          "decision": "BET",
          "edge": null,
          "game": "Los Angeles Dodgers @ San Diego Padres",
          "home_team": "San Diego Padres",
          "matchup": "Los Angeles Dodgers @ San Diego Padres",
          "odds": -222,
          "pick": "Total Under (9,5) (Los Angeles Dodgers @ San Diego Padres)",
          "pregame_snapshot": {
            "away_team": "Los Angeles Dodgers",
            "date": "2026-06-26",
            "decision": "BET",
            "edge": null,
            "game": "Los Angeles Dodgers @ San Diego Padres",
            "home_team": "San Diego Padres",
            "matchup": "Los Angeles Dodgers @ San Diego Padres",
            "odds": -222,
            "pick": "Total Under (9,5) (Los Angeles Dodgers @ San Diego Padres)",
            "probability": null,
            "source": "Scores24MLB",
            "source_url": "https://scores24.live/en/baseball/m-26-06-2026-san-diego-padres-los-angeles-dodgers-prediction",
            "sport": "MLB",
            "start_time": "2026-06-27T01:45Z",
            "tip": "Total Under (9,5)",
            "units": 1
          },
          "probability": null,
          "source": "Scores24MLB",
          "source_url": "https://scores24.live/en/baseball/m-26-06-2026-san-diego-padres-los-angeles-dodgers-prediction",
          "sport": "MLB",
          "start_time": "2026-06-27T01:45Z",
          "tip": "Total Under (9,5)",
          "units": 1
        }
      ],
      "updatedAt": "2026-06-26T13:04:04.811214Z"
    },
    "scores24_wnba": {
      "date": "2026-06-26",
      "generatedAt": "2026-06-26T13:04:04.811214Z",
      "generatedBy": "github-actions:external-feed-refresh",
      "meta": {
        "attemptedUrls": 3,
        "blockRetryRounds": 0,
        "blockedUrls": 0,
        "date": "2026-06-26",
        "expectedMatchups": 3,
        "feed": "scores24_wnba",
        "from": "github-actions",
        "leagues": "mlb,wnba,fifa_world_cup",
        "listingLinks": 11,
        "matchedPicks": 3,
        "missingMatchups": [],
        "officialMatchups": 3,
        "unpublishedMatchups": [],
        "updatedAt": "2026-06-26T13:04:04.811214Z"
      },
      "note": "Scores24WNBA matched 3 published editorial choice(s) against 3 official 2026-06-26 matchup(s).",
      "ok": true,
      "picks": [
        {
          "away_team": "Washington Mystics",
          "date": "2026-06-26",
          "decision": "BET",
          "edge": null,
          "game": "Washington Mystics @ Connecticut Sun",
          "home_team": "Connecticut Sun",
          "matchup": "Washington Mystics @ Connecticut Sun",
          "odds": -104,
          "pick": "Total points Under (162,5) (Washington Mystics @ Connecticut Sun)",
          "pregame_snapshot": {
            "away_team": "Washington Mystics",
            "date": "2026-06-26",
            "decision": "BET",
            "edge": null,
            "game": "Washington Mystics @ Connecticut Sun",
            "home_team": "Connecticut Sun",
            "matchup": "Washington Mystics @ Connecticut Sun",
            "odds": -104,
            "pick": "Total points Under (162,5) (Washington Mystics @ Connecticut Sun)",
            "probability": null,
            "source": "Scores24WNBA",
            "source_url": "https://scores24.live/en/basketball/m-26-06-2026-connecticut-sun-w-washington-mystics-w--prediction",
            "sport": "WNBA",
            "start_time": "2026-06-26T23:30Z",
            "tip": "Total points Under (162,5)",
            "units": 1
          },
          "probability": null,
          "source": "Scores24WNBA",
          "source_url": "https://scores24.live/en/basketball/m-26-06-2026-connecticut-sun-w-washington-mystics-w--prediction",
          "sport": "WNBA",
          "start_time": "2026-06-26T23:30Z",
          "tip": "Total points Under (162,5)",
          "units": 1
        },
        {
          "away_team": "Portland Fire",
          "date": "2026-06-26",
          "decision": "BET",
          "edge": null,
          "game": "Portland Fire @ Chicago Sky",
          "home_team": "Chicago Sky",
          "matchup": "Portland Fire @ Chicago Sky",
          "odds": -118,
          "pick": "Portland Fire (W) Total points Under (84,5) (Portland Fire @ Chicago Sky)",
          "pregame_snapshot": {
            "away_team": "Portland Fire",
            "date": "2026-06-26",
            "decision": "BET",
            "edge": null,
            "game": "Portland Fire @ Chicago Sky",
            "home_team": "Chicago Sky",
            "matchup": "Portland Fire @ Chicago Sky",
            "odds": -118,
            "pick": "Portland Fire (W) Total points Under (84,5) (Portland Fire @ Chicago Sky)",
            "probability": null,
            "source": "Scores24WNBA",
            "source_url": "https://scores24.live/en/basketball/m-26-06-2026-chicago-sky-w-portland-fire-prediction",
            "sport": "WNBA",
            "start_time": "2026-06-26T23:30Z",
            "tip": "Portland Fire (W) Total points Under (84,5)",
            "units": 1
          },
          "probability": null,
          "source": "Scores24WNBA",
          "source_url": "https://scores24.live/en/basketball/m-26-06-2026-chicago-sky-w-portland-fire-prediction",
          "sport": "WNBA",
          "start_time": "2026-06-26T23:30Z",
          "tip": "Portland Fire (W) Total points Under (84,5)",
          "units": 1
        },
        {
          "away_team": "Atlanta Dream",
          "date": "2026-06-26",
          "decision": "BET",
          "edge": null,
          "game": "Atlanta Dream @ Golden State Valkyries",
          "home_team": "Golden State Valkyries",
          "matchup": "Atlanta Dream @ Golden State Valkyries",
          "odds": -189,
          "pick": "Total points Over (156,5) (Atlanta Dream @ Golden State Valkyries)",
          "pregame_snapshot": {
            "away_team": "Atlanta Dream",
            "date": "2026-06-26",
            "decision": "BET",
            "edge": null,
            "game": "Atlanta Dream @ Golden State Valkyries",
            "home_team": "Golden State Valkyries",
            "matchup": "Atlanta Dream @ Golden State Valkyries",
            "odds": -189,
            "pick": "Total points Over (156,5) (Atlanta Dream @ Golden State Valkyries)",
            "probability": null,
            "source": "Scores24WNBA",
            "source_url": "https://scores24.live/en/basketball/m-27-06-2026-golden-state-valkyries-w-atlanta-dream-w--prediction",
            "sport": "WNBA",
            "start_time": "2026-06-27T02:00Z",
            "tip": "Total points Over (156,5)",
            "units": 1
          },
          "probability": null,
          "source": "Scores24WNBA",
          "source_url": "https://scores24.live/en/basketball/m-27-06-2026-golden-state-valkyries-w-atlanta-dream-w--prediction",
          "sport": "WNBA",
          "start_time": "2026-06-27T02:00Z",
          "tip": "Total points Over (156,5)",
          "units": 1
        }
      ],
      "updatedAt": "2026-06-26T13:04:04.811214Z"
    }
  },
  "models": {
    "scores24_fifa_world_cup": {
      "date": "2026-06-26",
      "generatedAt": "2026-06-26T13:04:04.811214Z",
      "generatedBy": "github-actions:external-feed-refresh",
      "meta": {
        "attemptedUrls": 6,
        "blockRetryRounds": 0,
        "blockedUrls": 0,
        "date": "2026-06-26",
        "expectedMatchups": 6,
        "feed": "scores24_fifa_world_cup",
        "from": "github-actions",
        "leagues": "mlb,wnba,fifa_world_cup",
        "listingLinks": 12,
        "matchedPicks": 6,
        "missingMatchups": [],
        "officialMatchups": 6,
        "unpublishedMatchups": [],
        "updatedAt": "2026-06-26T13:04:04.811214Z"
      },
      "note": "Scores24FIFAWorldCup matched 6 published editorial choice(s) against 6 official 2026-06-26 matchup(s).",
      "ok": true,
      "picks": [
        {
          "away_team": "France",
          "calibration_excluded": true,
          "date": "2026-06-26",
          "decision": "BET",
          "edge": null,
          "game": "France @ Norway",
          "grade_supported": false,
          "home_team": "Norway",
          "market_type": "soccer_specialty",
          "matchup": "France @ Norway",
          "odds": -152,
          "pick": "Both Teams To Score (Yes) (France @ Norway)",
          "probability": null,
          "source": "Scores24FIFAWorldCup",
          "source_url": "https://scores24.live/en/soccer/m-27-06-2026-norway-france-prediction",
          "sport": "FIFA WC",
          "start_time": "2026-06-26T19:00Z",
          "tip": "Both Teams To Score (Yes)",
          "units": 1
        },
        {
          "away_team": "Iraq",
          "calibration_excluded": true,
          "date": "2026-06-26",
          "decision": "BET",
          "edge": null,
          "game": "Iraq @ Senegal",
          "grade_supported": false,
          "home_team": "Senegal",
          "market_type": "soccer_specialty",
          "matchup": "Iraq @ Senegal",
          "odds": -152,
          "pick": "Senegal Handicap (-1,5) (Iraq @ Senegal)",
          "probability": null,
          "source": "Scores24FIFAWorldCup",
          "source_url": "https://scores24.live/en/soccer/m-26-06-2026-senegal-iraq-prediction",
          "sport": "FIFA WC",
          "start_time": "2026-06-26T19:00Z",
          "tip": "Senegal Handicap (-1,5)",
          "units": 1
        },
        {
          "away_team": "Saudi Arabia",
          "calibration_excluded": true,
          "date": "2026-06-26",
          "decision": "BET",
          "edge": null,
          "game": "Saudi Arabia @ Cape Verde",
          "grade_supported": false,
          "home_team": "Cape Verde",
          "market_type": "soccer_specialty",
          "matchup": "Saudi Arabia @ Cape Verde",
          "odds": -175,
          "pick": "Cape Verde Total goals Over (1) (Saudi Arabia @ Cape Verde)",
          "probability": null,
          "source": "Scores24FIFAWorldCup",
          "source_url": "https://scores24.live/en/soccer/m-27-06-2026-cape-verde-saudi-arabia-prediction",
          "sport": "FIFA WC",
          "start_time": "2026-06-27T00:00Z",
          "tip": "Cape Verde Total goals Over (1)",
          "units": 1
        },
        {
          "away_team": "Spain",
          "calibration_excluded": true,
          "date": "2026-06-26",
          "decision": "BET",
          "edge": null,
          "game": "Spain @ Uruguay",
          "grade_supported": false,
          "home_team": "Uruguay",
          "market_type": "soccer_specialty",
          "matchup": "Spain @ Uruguay",
          "odds": -108,
          "pick": "Both Teams To Score (Yes) (Spain @ Uruguay)",
          "probability": null,
          "source": "Scores24FIFAWorldCup",
          "source_url": "https://scores24.live/en/soccer/m-27-06-2026-uruguay-spain-prediction",
          "sport": "FIFA WC",
          "start_time": "2026-06-27T00:00Z",
          "tip": "Both Teams To Score (Yes)",
          "units": 1
        },
        {
          "away_team": "Iran",
          "calibration_excluded": true,
          "date": "2026-06-26",
          "decision": "BET",
          "edge": null,
          "game": "Iran @ Egypt",
          "grade_supported": false,
          "home_team": "Egypt",
          "market_type": "soccer_specialty",
          "matchup": "Iran @ Egypt",
          "odds": -175,
          "pick": "Egypt 0 (Iran @ Egypt)",
          "probability": null,
          "source": "Scores24FIFAWorldCup",
          "source_url": "https://scores24.live/en/soccer/m-27-06-2026-egypt-iran-prediction",
          "sport": "FIFA WC",
          "start_time": "2026-06-27T03:00Z",
          "tip": "Egypt Handicap (0)",
          "units": 1
        },
        {
          "away_team": "Belgium",
          "calibration_excluded": true,
          "date": "2026-06-26",
          "decision": "BET",
          "edge": null,
          "game": "Belgium @ New Zealand",
          "grade_supported": false,
          "home_team": "New Zealand",
          "market_type": "soccer_specialty",
          "matchup": "Belgium @ New Zealand",
          "odds": 129,
          "pick": "Both Teams To Score (Yes) (Belgium @ New Zealand)",
          "probability": null,
          "source": "Scores24FIFAWorldCup",
          "source_url": "https://scores24.live/en/soccer/m-27-06-2026-new-zealand-belgium-prediction",
          "sport": "FIFA WC",
          "start_time": "2026-06-27T03:00Z",
          "tip": "Both Teams To Score (Yes)",
          "units": 1
        }
      ],
      "updatedAt": "2026-06-26T13:04:04.811214Z"
    },
    "scores24_mlb": {
      "date": "2026-06-26",
      "generatedAt": "2026-06-26T13:04:04.811214Z",
      "generatedBy": "github-actions:external-feed-refresh",
      "meta": {
        "attemptedUrls": 20,
        "blockRetryRounds": 0,
        "blockedUrls": 0,
        "date": "2026-06-26",
        "expectedMatchups": 14,
        "feed": "scores24_mlb",
        "from": "github-actions",
        "leagues": "mlb,wnba,fifa_world_cup",
        "listingLinks": 12,
        "matchedPicks": 14,
        "missingMatchups": [],
        "officialMatchups": 15,
        "unpublishedMatchups": [
          "Atlanta Braves @ San Francisco Giants"
        ],
        "updatedAt": "2026-06-26T13:04:04.811214Z"
      },
      "note": "Scores24MLB matched 14 published editorial choice(s) against 15 official 2026-06-26 matchup(s).",
      "ok": true,
      "picks": [
        {
          "away_team": "Cincinnati Reds",
          "date": "2026-06-26",
          "decision": "BET",
          "edge": null,
          "game": "Cincinnati Reds @ Pittsburgh Pirates",
          "home_team": "Pittsburgh Pirates",
          "matchup": "Cincinnati Reds @ Pittsburgh Pirates",
          "odds": -217,
          "pick": "Pittsburgh Pirates ML (Cincinnati Reds @ Pittsburgh Pirates)",
          "pregame_snapshot": {
            "away_team": "Cincinnati Reds",
            "date": "2026-06-26",
            "decision": "BET",
            "edge": null,
            "game": "Cincinnati Reds @ Pittsburgh Pirates",
            "home_team": "Pittsburgh Pirates",
            "matchup": "Cincinnati Reds @ Pittsburgh Pirates",
            "odds": -217,
            "pick": "Pittsburgh Pirates ML (Cincinnati Reds @ Pittsburgh Pirates)",
            "probability": null,
            "source": "Scores24MLB",
            "source_url": "https://scores24.live/en/baseball/m-26-06-2026-pittsburgh-pirates-cincinnati-reds-prediction",
            "sport": "MLB",
            "start_time": "2026-06-26T22:40Z",
            "tip": "Pittsburgh Pirates Win",
            "units": 1
          },
          "probability": null,
          "source": "Scores24MLB",
          "source_url": "https://scores24.live/en/baseball/m-26-06-2026-pittsburgh-pirates-cincinnati-reds-prediction",
          "sport": "MLB",
          "start_time": "2026-06-26T22:40Z",
          "tip": "Pittsburgh Pirates Win",
          "units": 1
        },
        {
          "away_team": "Houston Astros",
          "date": "2026-06-26",
          "decision": "BET",
          "edge": null,
          "game": "Houston Astros @ Detroit Tigers",
          "home_team": "Detroit Tigers",
          "matchup": "Houston Astros @ Detroit Tigers",
          "odds": -189,
          "pick": "Total Under (9,5) (Houston Astros @ Detroit Tigers)",
          "pregame_snapshot": {
            "away_team": "Houston Astros",
            "date": "2026-06-26",
            "decision": "BET",
            "edge": null,
            "game": "Houston Astros @ Detroit Tigers",
            "home_team": "Detroit Tigers",
            "matchup": "Houston Astros @ Detroit Tigers",
            "odds": -189,
            "pick": "Total Under (9,5) (Houston Astros @ Detroit Tigers)",
            "probability": null,
            "source": "Scores24MLB",
            "source_url": "https://scores24.live/en/baseball/m-26-06-2026-detroit-tigers-houston-astros-prediction",
            "sport": "MLB",
            "start_time": "2026-06-26T22:40Z",
            "tip": "Total Under (9,5)",
            "units": 1
          },
          "probability": null,
          "source": "Scores24MLB",
          "source_url": "https://scores24.live/en/baseball/m-26-06-2026-detroit-tigers-houston-astros-prediction",
          "sport": "MLB",
          "start_time": "2026-06-26T22:40Z",
          "tip": "Total Under (9,5)",
          "units": 1
        },
        {
          "away_team": "Washington Nationals",
          "date": "2026-06-26",
          "decision": "BET",
          "edge": null,
          "game": "Washington Nationals @ Baltimore Orioles",
          "home_team": "Baltimore Orioles",
          "matchup": "Washington Nationals @ Baltimore Orioles",
          "odds": -152,
          "pick": "Total Under (9,5) (Washington Nationals @ Baltimore Orioles)",
          "pregame_snapshot": {
            "away_team": "Washington Nationals",
            "date": "2026-06-26",
            "decision": "BET",
            "edge": null,
            "game": "Washington Nationals @ Baltimore Orioles",
            "home_team": "Baltimore Orioles",
            "matchup": "Washington Nationals @ Baltimore Orioles",
            "odds": -152,
            "pick": "Total Under (9,5) (Washington Nationals @ Baltimore Orioles)",
            "probability": null,
            "source": "Scores24MLB",
            "source_url": "https://scores24.live/en/baseball/m-26-06-2026-baltimore-orioles-washington-nationals-prediction",
            "sport": "MLB",
            "start_time": "2026-06-26T23:05Z",
            "tip": "Total Under (9,5)",
            "units": 1
          },
          "probability": null,
          "source": "Scores24MLB",
          "source_url": "https://scores24.live/en/baseball/m-26-06-2026-baltimore-orioles-washington-nationals-prediction",
          "sport": "MLB",
          "start_time": "2026-06-26T23:05Z",
          "tip": "Total Under (9,5)",
          "units": 1
        },
        {
          "away_team": "Texas Rangers",
          "date": "2026-06-26",
          "decision": "BET",
          "edge": null,
          "game": "Texas Rangers @ Toronto Blue Jays",
          "home_team": "Toronto Blue Jays",
          "matchup": "Texas Rangers @ Toronto Blue Jays",
          "odds": -145,
          "pick": "Toronto Blue Jays Total Over (3,5) (Texas Rangers @ Toronto Blue Jays)",
          "pregame_snapshot": {
            "away_team": "Texas Rangers",
            "date": "2026-06-26",
            "decision": "BET",
            "edge": null,
            "game": "Texas Rangers @ Toronto Blue Jays",
            "home_team": "Toronto Blue Jays",
            "matchup": "Texas Rangers @ Toronto Blue Jays",
            "odds": -145,
            "pick": "Toronto Blue Jays Total Over (3,5) (Texas Rangers @ Toronto Blue Jays)",
            "probability": null,
            "source": "Scores24MLB",
            "source_url": "https://scores24.live/en/baseball/m-26-06-2026-toronto-blue-jays-texas-rangers-prediction",
            "sport": "MLB",
            "start_time": "2026-06-26T23:07Z",
            "tip": "Toronto Blue Jays Total Over (3,5)",
            "units": 1
          },
          "probability": null,
          "source": "Scores24MLB",
          "source_url": "https://scores24.live/en/baseball/m-26-06-2026-toronto-blue-jays-texas-rangers-prediction",
          "sport": "MLB",
          "start_time": "2026-06-26T23:07Z",
          "tip": "Toronto Blue Jays Total Over (3,5)",
          "units": 1
        },
        {
          "away_team": "Arizona Diamondbacks",
          "date": "2026-06-26",
          "decision": "BET",
          "edge": null,
          "game": "Arizona Diamondbacks @ Tampa Bay Rays",
          "home_team": "Tampa Bay Rays",
          "matchup": "Arizona Diamondbacks @ Tampa Bay Rays",
          "odds": -141,
          "pick": "Tampa Bay Rays ML (Arizona Diamondbacks @ Tampa Bay Rays)",
          "pregame_snapshot": {
            "away_team": "Arizona Diamondbacks",
            "date": "2026-06-26",
            "decision": "BET",
            "edge": null,
            "game": "Arizona Diamondbacks @ Tampa Bay Rays",
            "home_team": "Tampa Bay Rays",
            "matchup": "Arizona Diamondbacks @ Tampa Bay Rays",
            "odds": -141,
            "pick": "Tampa Bay Rays ML (Arizona Diamondbacks @ Tampa Bay Rays)",
            "probability": null,
            "source": "Scores24MLB",
            "source_url": "https://scores24.live/en/baseball/m-26-06-2026-tampa-bay-rays-arizona-diamondbacks-prediction",
            "sport": "MLB",
            "start_time": "2026-06-26T23:10Z",
            "tip": "Tampa Bay Rays Win",
            "units": 1
          },
          "probability": null,
          "source": "Scores24MLB",
          "source_url": "https://scores24.live/en/baseball/m-26-06-2026-tampa-bay-rays-arizona-diamondbacks-prediction",
          "sport": "MLB",
          "start_time": "2026-06-26T23:10Z",
          "tip": "Tampa Bay Rays Win",
          "units": 1
        },
        {
          "away_team": "New York Yankees",
          "date": "2026-06-26",
          "decision": "BET",
          "edge": null,
          "game": "New York Yankees @ Boston Red Sox",
          "home_team": "Boston Red Sox",
          "matchup": "New York Yankees @ Boston Red Sox",
          "odds": -161,
          "pick": "Total Under (9,5) (New York Yankees @ Boston Red Sox)",
          "pregame_snapshot": {
            "away_team": "New York Yankees",
            "date": "2026-06-26",
            "decision": "BET",
            "edge": null,
            "game": "New York Yankees @ Boston Red Sox",
            "home_team": "Boston Red Sox",
            "matchup": "New York Yankees @ Boston Red Sox",
            "odds": -161,
            "pick": "Total Under (9,5) (New York Yankees @ Boston Red Sox)",
            "probability": null,
            "source": "Scores24MLB",
            "source_url": "https://scores24.live/en/baseball/m-26-06-2026-boston-red-sox-new-york-yankees-prediction",
            "sport": "MLB",
            "start_time": "2026-06-26T23:10Z",
            "tip": "Total Under (9,5)",
            "units": 1
          },
          "probability": null,
          "source": "Scores24MLB",
          "source_url": "https://scores24.live/en/baseball/m-26-06-2026-boston-red-sox-new-york-yankees-prediction",
          "sport": "MLB",
          "start_time": "2026-06-26T23:10Z",
          "tip": "Total Under (9,5)",
          "units": 1
        },
        {
          "away_team": "Philadelphia Phillies",
          "date": "2026-06-26",
          "decision": "BET",
          "edge": null,
          "game": "Philadelphia Phillies @ New York Mets",
          "home_team": "New York Mets",
          "matchup": "Philadelphia Phillies @ New York Mets",
          "odds": -159,
          "pick": "Philadelphia Phillies ML (Philadelphia Phillies @ New York Mets)",
          "pregame_snapshot": {
            "away_team": "Philadelphia Phillies",
            "date": "2026-06-26",
            "decision": "BET",
            "edge": null,
            "game": "Philadelphia Phillies @ New York Mets",
            "home_team": "New York Mets",
            "matchup": "Philadelphia Phillies @ New York Mets",
            "odds": -159,
            "pick": "Philadelphia Phillies ML (Philadelphia Phillies @ New York Mets)",
            "probability": null,
            "source": "Scores24MLB",
            "source_url": "https://scores24.live/en/baseball/m-26-06-2026-new-york-mets-philadelphia-phillies-prediction",
            "sport": "MLB",
            "start_time": "2026-06-26T23:10Z",
            "tip": "Philadelphia Phillies Win",
            "units": 1
          },
          "probability": null,
          "source": "Scores24MLB",
          "source_url": "https://scores24.live/en/baseball/m-26-06-2026-new-york-mets-philadelphia-phillies-prediction",
          "sport": "MLB",
          "start_time": "2026-06-26T23:10Z",
          "tip": "Philadelphia Phillies Win",
          "units": 1
        },
        {
          "away_team": "Seattle Mariners",
          "date": "2026-06-26",
          "decision": "BET",
          "edge": null,
          "game": "Seattle Mariners @ Cleveland Guardians",
          "home_team": "Cleveland Guardians",
          "matchup": "Seattle Mariners @ Cleveland Guardians",
          "odds": -112,
          "pick": "Cleveland Gardians ML (Seattle Mariners @ Cleveland Guardians)",
          "pregame_snapshot": {
            "away_team": "Seattle Mariners",
            "date": "2026-06-26",
            "decision": "BET",
            "edge": null,
            "game": "Seattle Mariners @ Cleveland Guardians",
            "home_team": "Cleveland Guardians",
            "matchup": "Seattle Mariners @ Cleveland Guardians",
            "odds": -112,
            "pick": "Cleveland Gardians ML (Seattle Mariners @ Cleveland Guardians)",
            "probability": null,
            "source": "Scores24MLB",
            "source_url": "https://scores24.live/en/baseball/m-26-06-2026-cleveland-guardians-seattle-mariners-prediction",
            "sport": "MLB",
            "start_time": "2026-06-26T23:10Z",
            "tip": "Cleveland Gardians Win",
            "units": 1
          },
          "probability": null,
          "source": "Scores24MLB",
          "source_url": "https://scores24.live/en/baseball/m-26-06-2026-cleveland-guardians-seattle-mariners-prediction",
          "sport": "MLB",
          "start_time": "2026-06-26T23:10Z",
          "tip": "Cleveland Gardians Win",
          "units": 1
        },
        {
          "away_team": "Kansas City Royals",
          "date": "2026-06-26",
          "decision": "BET",
          "edge": null,
          "game": "Kansas City Royals @ Chicago White Sox",
          "home_team": "Chicago White Sox",
          "matchup": "Kansas City Royals @ Chicago White Sox",
          "odds": -137,
          "pick": "Total Over (7,5) (Kansas City Royals @ Chicago White Sox)",
          "pregame_snapshot": {
            "away_team": "Kansas City Royals",
            "date": "2026-06-26",
            "decision": "BET",
            "edge": null,
            "game": "Kansas City Royals @ Chicago White Sox",
            "home_team": "Chicago White Sox",
            "matchup": "Kansas City Royals @ Chicago White Sox",
            "odds": -137,
            "pick": "Total Over (7,5) (Kansas City Royals @ Chicago White Sox)",
            "probability": null,
            "source": "Scores24MLB",
            "source_url": "https://scores24.live/en/baseball/m-26-06-2026-chicago-white-sox-kansas-city-royals-prediction",
            "sport": "MLB",
            "start_time": "2026-06-26T23:40Z",
            "tip": "Total Over (7,5)",
            "units": 1
          },
          "probability": null,
          "source": "Scores24MLB",
          "source_url": "https://scores24.live/en/baseball/m-26-06-2026-chicago-white-sox-kansas-city-royals-prediction",
          "sport": "MLB",
          "start_time": "2026-06-26T23:40Z",
          "tip": "Total Over (7,5)",
          "units": 1
        },
        {
          "away_team": "Chicago Cubs",
          "date": "2026-06-26",
          "decision": "BET",
          "edge": null,
          "game": "Chicago Cubs @ Milwaukee Brewers",
          "home_team": "Milwaukee Brewers",
          "matchup": "Chicago Cubs @ Milwaukee Brewers",
          "odds": -189,
          "pick": "Total Over (6,5) (Chicago Cubs @ Milwaukee Brewers)",
          "pregame_snapshot": {
            "away_team": "Chicago Cubs",
            "date": "2026-06-26",
            "decision": "BET",
            "edge": null,
            "game": "Chicago Cubs @ Milwaukee Brewers",
            "home_team": "Milwaukee Brewers",
            "matchup": "Chicago Cubs @ Milwaukee Brewers",
            "odds": -189,
            "pick": "Total Over (6,5) (Chicago Cubs @ Milwaukee Brewers)",
            "probability": null,
            "source": "Scores24MLB",
            "source_url": "https://scores24.live/en/baseball/m-26-06-2026-milwaukee-brewers-chicago-cubs-prediction",
            "sport": "MLB",
            "start_time": "2026-06-26T23:45Z",
            "tip": "Total Over (6,5)",
            "units": 1
          },
          "probability": null,
          "source": "Scores24MLB",
          "source_url": "https://scores24.live/en/baseball/m-26-06-2026-milwaukee-brewers-chicago-cubs-prediction",
          "sport": "MLB",
          "start_time": "2026-06-26T23:45Z",
          "tip": "Total Over (6,5)",
          "units": 1
        },
        {
          "away_team": "Colorado Rockies",
          "date": "2026-06-26",
          "decision": "BET",
          "edge": null,
          "game": "Colorado Rockies @ Minnesota Twins",
          "home_team": "Minnesota Twins",
          "matchup": "Colorado Rockies @ Minnesota Twins",
          "odds": -141,
          "pick": "Total Over (8,5) (Colorado Rockies @ Minnesota Twins)",
          "pregame_snapshot": {
            "away_team": "Colorado Rockies",
            "date": "2026-06-26",
            "decision": "BET",
            "edge": null,
            "game": "Colorado Rockies @ Minnesota Twins",
            "home_team": "Minnesota Twins",
            "matchup": "Colorado Rockies @ Minnesota Twins",
            "odds": -141,
            "pick": "Total Over (8,5) (Colorado Rockies @ Minnesota Twins)",
            "probability": null,
            "source": "Scores24MLB",
            "source_url": "https://scores24.live/en/baseball/m-26-06-2026-minnesota-twins-colorado-rockies-prediction",
            "sport": "MLB",
            "start_time": "2026-06-27T00:10Z",
            "tip": "Total Over (8,5)",
            "units": 1
          },
          "probability": null,
          "source": "Scores24MLB",
          "source_url": "https://scores24.live/en/baseball/m-26-06-2026-minnesota-twins-colorado-rockies-prediction",
          "sport": "MLB",
          "start_time": "2026-06-27T00:10Z",
          "tip": "Total Over (8,5)",
          "units": 1
        },
        {
          "away_team": "Miami Marlins",
          "date": "2026-06-26",
          "decision": "BET",
          "edge": null,
          "game": "Miami Marlins @ St. Louis Cardinals",
          "home_team": "St. Louis Cardinals",
          "matchup": "Miami Marlins @ St. Louis Cardinals",
          "odds": 100,
          "pick": "Miami Marlins ML (Miami Marlins @ St. Louis Cardinals)",
          "pregame_snapshot": {
            "away_team": "Miami Marlins",
            "date": "2026-06-26",
            "decision": "BET",
            "edge": null,
            "game": "Miami Marlins @ St. Louis Cardinals",
            "home_team": "St. Louis Cardinals",
            "matchup": "Miami Marlins @ St. Louis Cardinals",
            "odds": 100,
            "pick": "Miami Marlins ML (Miami Marlins @ St. Louis Cardinals)",
            "probability": null,
            "source": "Scores24MLB",
            "source_url": "https://scores24.live/en/baseball/m-26-06-2026-st-louis-cardinals-miami-marlins-prediction",
            "sport": "MLB",
            "start_time": "2026-06-27T00:15Z",
            "tip": "Miami Marlins Win",
            "units": 1
          },
          "probability": null,
          "source": "Scores24MLB",
          "source_url": "https://scores24.live/en/baseball/m-26-06-2026-st-louis-cardinals-miami-marlins-prediction",
          "sport": "MLB",
          "start_time": "2026-06-27T00:15Z",
          "tip": "Miami Marlins Win",
          "units": 1
        },
        {
          "away_team": "Athletics",
          "date": "2026-06-26",
          "decision": "BET",
          "edge": null,
          "game": "Athletics @ Los Angeles Angels",
          "home_team": "Los Angeles Angels",
          "matchup": "Athletics @ Los Angeles Angels",
          "odds": -167,
          "pick": "Total Under (9,5) (Athletics @ Los Angeles Angels)",
          "pregame_snapshot": {
            "away_team": "Athletics",
            "date": "2026-06-26",
            "decision": "BET",
            "edge": null,
            "game": "Athletics @ Los Angeles Angels",
            "home_team": "Los Angeles Angels",
            "matchup": "Athletics @ Los Angeles Angels",
            "odds": -167,
            "pick": "Total Under (9,5) (Athletics @ Los Angeles Angels)",
            "probability": null,
            "source": "Scores24MLB",
            "source_url": "https://scores24.live/en/baseball/m-26-06-2026-los-angeles-angels-athletics-prediction",
            "sport": "MLB",
            "start_time": "2026-06-27T01:38Z",
            "tip": "Total Under (9,5)",
            "units": 1
          },
          "probability": null,
          "source": "Scores24MLB",
          "source_url": "https://scores24.live/en/baseball/m-26-06-2026-los-angeles-angels-athletics-prediction",
          "sport": "MLB",
          "start_time": "2026-06-27T01:38Z",
          "tip": "Total Under (9,5)",
          "units": 1
        },
        {
          "away_team": "Los Angeles Dodgers",
          "date": "2026-06-26",
          "decision": "BET",
          "edge": null,
          "game": "Los Angeles Dodgers @ San Diego Padres",
          "home_team": "San Diego Padres",
          "matchup": "Los Angeles Dodgers @ San Diego Padres",
          "odds": -222,
          "pick": "Total Under (9,5) (Los Angeles Dodgers @ San Diego Padres)",
          "pregame_snapshot": {
            "away_team": "Los Angeles Dodgers",
            "date": "2026-06-26",
            "decision": "BET",
            "edge": null,
            "game": "Los Angeles Dodgers @ San Diego Padres",
            "home_team": "San Diego Padres",
            "matchup": "Los Angeles Dodgers @ San Diego Padres",
            "odds": -222,
            "pick": "Total Under (9,5) (Los Angeles Dodgers @ San Diego Padres)",
            "probability": null,
            "source": "Scores24MLB",
            "source_url": "https://scores24.live/en/baseball/m-26-06-2026-san-diego-padres-los-angeles-dodgers-prediction",
            "sport": "MLB",
            "start_time": "2026-06-27T01:45Z",
            "tip": "Total Under (9,5)",
            "units": 1
          },
          "probability": null,
          "source": "Scores24MLB",
          "source_url": "https://scores24.live/en/baseball/m-26-06-2026-san-diego-padres-los-angeles-dodgers-prediction",
          "sport": "MLB",
          "start_time": "2026-06-27T01:45Z",
          "tip": "Total Under (9,5)",
          "units": 1
        }
      ],
      "updatedAt": "2026-06-26T13:04:04.811214Z"
    },
    "scores24_wnba": {
      "date": "2026-06-26",
      "generatedAt": "2026-06-26T13:04:04.811214Z",
      "generatedBy": "github-actions:external-feed-refresh",
      "meta": {
        "attemptedUrls": 3,
        "blockRetryRounds": 0,
        "blockedUrls": 0,
        "date": "2026-06-26",
        "expectedMatchups": 3,
        "feed": "scores24_wnba",
        "from": "github-actions",
        "leagues": "mlb,wnba,fifa_world_cup",
        "listingLinks": 11,
        "matchedPicks": 3,
        "missingMatchups": [],
        "officialMatchups": 3,
        "unpublishedMatchups": [],
        "updatedAt": "2026-06-26T13:04:04.811214Z"
      },
      "note": "Scores24WNBA matched 3 published editorial choice(s) against 3 official 2026-06-26 matchup(s).",
      "ok": true,
      "picks": [
        {
          "away_team": "Washington Mystics",
          "date": "2026-06-26",
          "decision": "BET",
          "edge": null,
          "game": "Washington Mystics @ Connecticut Sun",
          "home_team": "Connecticut Sun",
          "matchup": "Washington Mystics @ Connecticut Sun",
          "odds": -104,
          "pick": "Total points Under (162,5) (Washington Mystics @ Connecticut Sun)",
          "pregame_snapshot": {
            "away_team": "Washington Mystics",
            "date": "2026-06-26",
            "decision": "BET",
            "edge": null,
            "game": "Washington Mystics @ Connecticut Sun",
            "home_team": "Connecticut Sun",
            "matchup": "Washington Mystics @ Connecticut Sun",
            "odds": -104,
            "pick": "Total points Under (162,5) (Washington Mystics @ Connecticut Sun)",
            "probability": null,
            "source": "Scores24WNBA",
            "source_url": "https://scores24.live/en/basketball/m-26-06-2026-connecticut-sun-w-washington-mystics-w--prediction",
            "sport": "WNBA",
            "start_time": "2026-06-26T23:30Z",
            "tip": "Total points Under (162,5)",
            "units": 1
          },
          "probability": null,
          "source": "Scores24WNBA",
          "source_url": "https://scores24.live/en/basketball/m-26-06-2026-connecticut-sun-w-washington-mystics-w--prediction",
          "sport": "WNBA",
          "start_time": "2026-06-26T23:30Z",
          "tip": "Total points Under (162,5)",
          "units": 1
        },
        {
          "away_team": "Portland Fire",
          "date": "2026-06-26",
          "decision": "BET",
          "edge": null,
          "game": "Portland Fire @ Chicago Sky",
          "home_team": "Chicago Sky",
          "matchup": "Portland Fire @ Chicago Sky",
          "odds": -118,
          "pick": "Portland Fire (W) Total points Under (84,5) (Portland Fire @ Chicago Sky)",
          "pregame_snapshot": {
            "away_team": "Portland Fire",
            "date": "2026-06-26",
            "decision": "BET",
            "edge": null,
            "game": "Portland Fire @ Chicago Sky",
            "home_team": "Chicago Sky",
            "matchup": "Portland Fire @ Chicago Sky",
            "odds": -118,
            "pick": "Portland Fire (W) Total points Under (84,5) (Portland Fire @ Chicago Sky)",
            "probability": null,
            "source": "Scores24WNBA",
            "source_url": "https://scores24.live/en/basketball/m-26-06-2026-chicago-sky-w-portland-fire-prediction",
            "sport": "WNBA",
            "start_time": "2026-06-26T23:30Z",
            "tip": "Portland Fire (W) Total points Under (84,5)",
            "units": 1
          },
          "probability": null,
          "source": "Scores24WNBA",
          "source_url": "https://scores24.live/en/basketball/m-26-06-2026-chicago-sky-w-portland-fire-prediction",
          "sport": "WNBA",
          "start_time": "2026-06-26T23:30Z",
          "tip": "Portland Fire (W) Total points Under (84,5)",
          "units": 1
        },
        {
          "away_team": "Atlanta Dream",
          "date": "2026-06-26",
          "decision": "BET",
          "edge": null,
          "game": "Atlanta Dream @ Golden State Valkyries",
          "home_team": "Golden State Valkyries",
          "matchup": "Atlanta Dream @ Golden State Valkyries",
          "odds": -189,
          "pick": "Total points Over (156,5) (Atlanta Dream @ Golden State Valkyries)",
          "pregame_snapshot": {
            "away_team": "Atlanta Dream",
            "date": "2026-06-26",
            "decision": "BET",
            "edge": null,
            "game": "Atlanta Dream @ Golden State Valkyries",
            "home_team": "Golden State Valkyries",
            "matchup": "Atlanta Dream @ Golden State Valkyries",
            "odds": -189,
            "pick": "Total points Over (156,5) (Atlanta Dream @ Golden State Valkyries)",
            "probability": null,
            "source": "Scores24WNBA",
            "source_url": "https://scores24.live/en/basketball/m-27-06-2026-golden-state-valkyries-w-atlanta-dream-w--prediction",
            "sport": "WNBA",
            "start_time": "2026-06-27T02:00Z",
            "tip": "Total points Over (156,5)",
            "units": 1
          },
          "probability": null,
          "source": "Scores24WNBA",
          "source_url": "https://scores24.live/en/basketball/m-27-06-2026-golden-state-valkyries-w-atlanta-dream-w--prediction",
          "sport": "WNBA",
          "start_time": "2026-06-27T02:00Z",
          "tip": "Total points Over (156,5)",
          "units": 1
        }
      ],
      "updatedAt": "2026-06-26T13:04:04.811214Z"
    }
  },
  "scores24_fifa_world_cup": {
    "date": "2026-06-26",
    "generatedAt": "2026-06-26T13:04:04.811214Z",
    "generatedBy": "github-actions:external-feed-refresh",
    "meta": {
      "attemptedUrls": 6,
      "blockRetryRounds": 0,
      "blockedUrls": 0,
      "date": "2026-06-26",
      "expectedMatchups": 6,
      "feed": "scores24_fifa_world_cup",
      "from": "github-actions",
      "leagues": "mlb,wnba,fifa_world_cup",
      "listingLinks": 12,
      "matchedPicks": 6,
      "missingMatchups": [],
      "officialMatchups": 6,
      "unpublishedMatchups": [],
      "updatedAt": "2026-06-26T13:04:04.811214Z"
    },
    "note": "Scores24FIFAWorldCup matched 6 published editorial choice(s) against 6 official 2026-06-26 matchup(s).",
    "ok": true,
    "picks": [
      {
        "away_team": "France",
        "calibration_excluded": true,
        "date": "2026-06-26",
        "decision": "BET",
        "edge": null,
        "game": "France @ Norway",
        "grade_supported": false,
        "home_team": "Norway",
        "market_type": "soccer_specialty",
        "matchup": "France @ Norway",
        "odds": -152,
        "pick": "Both Teams To Score (Yes) (France @ Norway)",
        "probability": null,
        "source": "Scores24FIFAWorldCup",
        "source_url": "https://scores24.live/en/soccer/m-27-06-2026-norway-france-prediction",
        "sport": "FIFA WC",
        "start_time": "2026-06-26T19:00Z",
        "tip": "Both Teams To Score (Yes)",
        "units": 1
      },
      {
        "away_team": "Iraq",
        "calibration_excluded": true,
        "date": "2026-06-26",
        "decision": "BET",
        "edge": null,
        "game": "Iraq @ Senegal",
        "grade_supported": false,
        "home_team": "Senegal",
        "market_type": "soccer_specialty",
        "matchup": "Iraq @ Senegal",
        "odds": -152,
        "pick": "Senegal Handicap (-1,5) (Iraq @ Senegal)",
        "probability": null,
        "source": "Scores24FIFAWorldCup",
        "source_url": "https://scores24.live/en/soccer/m-26-06-2026-senegal-iraq-prediction",
        "sport": "FIFA WC",
        "start_time": "2026-06-26T19:00Z",
        "tip": "Senegal Handicap (-1,5)",
        "units": 1
      },
      {
        "away_team": "Saudi Arabia",
        "calibration_excluded": true,
        "date": "2026-06-26",
        "decision": "BET",
        "edge": null,
        "game": "Saudi Arabia @ Cape Verde",
        "grade_supported": false,
        "home_team": "Cape Verde",
        "market_type": "soccer_specialty",
        "matchup": "Saudi Arabia @ Cape Verde",
        "odds": -175,
        "pick": "Cape Verde Total goals Over (1) (Saudi Arabia @ Cape Verde)",
        "probability": null,
        "source": "Scores24FIFAWorldCup",
        "source_url": "https://scores24.live/en/soccer/m-27-06-2026-cape-verde-saudi-arabia-prediction",
        "sport": "FIFA WC",
        "start_time": "2026-06-27T00:00Z",
        "tip": "Cape Verde Total goals Over (1)",
        "units": 1
      },
      {
        "away_team": "Spain",
        "calibration_excluded": true,
        "date": "2026-06-26",
        "decision": "BET",
        "edge": null,
        "game": "Spain @ Uruguay",
        "grade_supported": false,
        "home_team": "Uruguay",
        "market_type": "soccer_specialty",
        "matchup": "Spain @ Uruguay",
        "odds": -108,
        "pick": "Both Teams To Score (Yes) (Spain @ Uruguay)",
        "probability": null,
        "source": "Scores24FIFAWorldCup",
        "source_url": "https://scores24.live/en/soccer/m-27-06-2026-uruguay-spain-prediction",
        "sport": "FIFA WC",
        "start_time": "2026-06-27T00:00Z",
        "tip": "Both Teams To Score (Yes)",
        "units": 1
      },
      {
        "away_team": "Iran",
        "calibration_excluded": true,
        "date": "2026-06-26",
        "decision": "BET",
        "edge": null,
        "game": "Iran @ Egypt",
        "grade_supported": false,
        "home_team": "Egypt",
        "market_type": "soccer_specialty",
        "matchup": "Iran @ Egypt",
        "odds": -175,
        "pick": "Egypt 0 (Iran @ Egypt)",
        "probability": null,
        "source": "Scores24FIFAWorldCup",
        "source_url": "https://scores24.live/en/soccer/m-27-06-2026-egypt-iran-prediction",
        "sport": "FIFA WC",
        "start_time": "2026-06-27T03:00Z",
        "tip": "Egypt Handicap (0)",
        "units": 1
      },
      {
        "away_team": "Belgium",
        "calibration_excluded": true,
        "date": "2026-06-26",
        "decision": "BET",
        "edge": null,
        "game": "Belgium @ New Zealand",
        "grade_supported": false,
        "home_team": "New Zealand",
        "market_type": "soccer_specialty",
        "matchup": "Belgium @ New Zealand",
        "odds": 129,
        "pick": "Both Teams To Score (Yes) (Belgium @ New Zealand)",
        "probability": null,
        "source": "Scores24FIFAWorldCup",
        "source_url": "https://scores24.live/en/soccer/m-27-06-2026-new-zealand-belgium-prediction",
        "sport": "FIFA WC",
        "start_time": "2026-06-27T03:00Z",
        "tip": "Both Teams To Score (Yes)",
        "units": 1
      }
    ],
    "updatedAt": "2026-06-26T13:04:04.811214Z"
  },
  "scores24_mlb": {
    "date": "2026-06-26",
    "generatedAt": "2026-06-26T13:04:04.811214Z",
    "generatedBy": "github-actions:external-feed-refresh",
    "meta": {
      "attemptedUrls": 20,
      "blockRetryRounds": 0,
      "blockedUrls": 0,
      "date": "2026-06-26",
      "expectedMatchups": 14,
      "feed": "scores24_mlb",
      "from": "github-actions",
      "leagues": "mlb,wnba,fifa_world_cup",
      "listingLinks": 12,
      "matchedPicks": 14,
      "missingMatchups": [],
      "officialMatchups": 15,
      "unpublishedMatchups": [
        "Atlanta Braves @ San Francisco Giants"
      ],
      "updatedAt": "2026-06-26T13:04:04.811214Z"
    },
    "note": "Scores24MLB matched 14 published editorial choice(s) against 15 official 2026-06-26 matchup(s).",
    "ok": true,
    "picks": [
      {
        "away_team": "Cincinnati Reds",
        "date": "2026-06-26",
        "decision": "BET",
        "edge": null,
        "game": "Cincinnati Reds @ Pittsburgh Pirates",
        "home_team": "Pittsburgh Pirates",
        "matchup": "Cincinnati Reds @ Pittsburgh Pirates",
        "odds": -217,
        "pick": "Pittsburgh Pirates ML (Cincinnati Reds @ Pittsburgh Pirates)",
        "pregame_snapshot": {
          "away_team": "Cincinnati Reds",
          "date": "2026-06-26",
          "decision": "BET",
          "edge": null,
          "game": "Cincinnati Reds @ Pittsburgh Pirates",
          "home_team": "Pittsburgh Pirates",
          "matchup": "Cincinnati Reds @ Pittsburgh Pirates",
          "odds": -217,
          "pick": "Pittsburgh Pirates ML (Cincinnati Reds @ Pittsburgh Pirates)",
          "probability": null,
          "source": "Scores24MLB",
          "source_url": "https://scores24.live/en/baseball/m-26-06-2026-pittsburgh-pirates-cincinnati-reds-prediction",
          "sport": "MLB",
          "start_time": "2026-06-26T22:40Z",
          "tip": "Pittsburgh Pirates Win",
          "units": 1
        },
        "probability": null,
        "source": "Scores24MLB",
        "source_url": "https://scores24.live/en/baseball/m-26-06-2026-pittsburgh-pirates-cincinnati-reds-prediction",
        "sport": "MLB",
        "start_time": "2026-06-26T22:40Z",
        "tip": "Pittsburgh Pirates Win",
        "units": 1
      },
      {
        "away_team": "Houston Astros",
        "date": "2026-06-26",
        "decision": "BET",
        "edge": null,
        "game": "Houston Astros @ Detroit Tigers",
        "home_team": "Detroit Tigers",
        "matchup": "Houston Astros @ Detroit Tigers",
        "odds": -189,
        "pick": "Total Under (9,5) (Houston Astros @ Detroit Tigers)",
        "pregame_snapshot": {
          "away_team": "Houston Astros",
          "date": "2026-06-26",
          "decision": "BET",
          "edge": null,
          "game": "Houston Astros @ Detroit Tigers",
          "home_team": "Detroit Tigers",
          "matchup": "Houston Astros @ Detroit Tigers",
          "odds": -189,
          "pick": "Total Under (9,5) (Houston Astros @ Detroit Tigers)",
          "probability": null,
          "source": "Scores24MLB",
          "source_url": "https://scores24.live/en/baseball/m-26-06-2026-detroit-tigers-houston-astros-prediction",
          "sport": "MLB",
          "start_time": "2026-06-26T22:40Z",
          "tip": "Total Under (9,5)",
          "units": 1
        },
        "probability": null,
        "source": "Scores24MLB",
        "source_url": "https://scores24.live/en/baseball/m-26-06-2026-detroit-tigers-houston-astros-prediction",
        "sport": "MLB",
        "start_time": "2026-06-26T22:40Z",
        "tip": "Total Under (9,5)",
        "units": 1
      },
      {
        "away_team": "Washington Nationals",
        "date": "2026-06-26",
        "decision": "BET",
        "edge": null,
        "game": "Washington Nationals @ Baltimore Orioles",
        "home_team": "Baltimore Orioles",
        "matchup": "Washington Nationals @ Baltimore Orioles",
        "odds": -152,
        "pick": "Total Under (9,5) (Washington Nationals @ Baltimore Orioles)",
        "pregame_snapshot": {
          "away_team": "Washington Nationals",
          "date": "2026-06-26",
          "decision": "BET",
          "edge": null,
          "game": "Washington Nationals @ Baltimore Orioles",
          "home_team": "Baltimore Orioles",
          "matchup": "Washington Nationals @ Baltimore Orioles",
          "odds": -152,
          "pick": "Total Under (9,5) (Washington Nationals @ Baltimore Orioles)",
          "probability": null,
          "source": "Scores24MLB",
          "source_url": "https://scores24.live/en/baseball/m-26-06-2026-baltimore-orioles-washington-nationals-prediction",
          "sport": "MLB",
          "start_time": "2026-06-26T23:05Z",
          "tip": "Total Under (9,5)",
          "units": 1
        },
        "probability": null,
        "source": "Scores24MLB",
        "source_url": "https://scores24.live/en/baseball/m-26-06-2026-baltimore-orioles-washington-nationals-prediction",
        "sport": "MLB",
        "start_time": "2026-06-26T23:05Z",
        "tip": "Total Under (9,5)",
        "units": 1
      },
      {
        "away_team": "Texas Rangers",
        "date": "2026-06-26",
        "decision": "BET",
        "edge": null,
        "game": "Texas Rangers @ Toronto Blue Jays",
        "home_team": "Toronto Blue Jays",
        "matchup": "Texas Rangers @ Toronto Blue Jays",
        "odds": -145,
        "pick": "Toronto Blue Jays Total Over (3,5) (Texas Rangers @ Toronto Blue Jays)",
        "pregame_snapshot": {
          "away_team": "Texas Rangers",
          "date": "2026-06-26",
          "decision": "BET",
          "edge": null,
          "game": "Texas Rangers @ Toronto Blue Jays",
          "home_team": "Toronto Blue Jays",
          "matchup": "Texas Rangers @ Toronto Blue Jays",
          "odds": -145,
          "pick": "Toronto Blue Jays Total Over (3,5) (Texas Rangers @ Toronto Blue Jays)",
          "probability": null,
          "source": "Scores24MLB",
          "source_url": "https://scores24.live/en/baseball/m-26-06-2026-toronto-blue-jays-texas-rangers-prediction",
          "sport": "MLB",
          "start_time": "2026-06-26T23:07Z",
          "tip": "Toronto Blue Jays Total Over (3,5)",
          "units": 1
        },
        "probability": null,
        "source": "Scores24MLB",
        "source_url": "https://scores24.live/en/baseball/m-26-06-2026-toronto-blue-jays-texas-rangers-prediction",
        "sport": "MLB",
        "start_time": "2026-06-26T23:07Z",
        "tip": "Toronto Blue Jays Total Over (3,5)",
        "units": 1
      },
      {
        "away_team": "Arizona Diamondbacks",
        "date": "2026-06-26",
        "decision": "BET",
        "edge": null,
        "game": "Arizona Diamondbacks @ Tampa Bay Rays",
        "home_team": "Tampa Bay Rays",
        "matchup": "Arizona Diamondbacks @ Tampa Bay Rays",
        "odds": -141,
        "pick": "Tampa Bay Rays ML (Arizona Diamondbacks @ Tampa Bay Rays)",
        "pregame_snapshot": {
          "away_team": "Arizona Diamondbacks",
          "date": "2026-06-26",
          "decision": "BET",
          "edge": null,
          "game": "Arizona Diamondbacks @ Tampa Bay Rays",
          "home_team": "Tampa Bay Rays",
          "matchup": "Arizona Diamondbacks @ Tampa Bay Rays",
          "odds": -141,
          "pick": "Tampa Bay Rays ML (Arizona Diamondbacks @ Tampa Bay Rays)",
          "probability": null,
          "source": "Scores24MLB",
          "source_url": "https://scores24.live/en/baseball/m-26-06-2026-tampa-bay-rays-arizona-diamondbacks-prediction",
          "sport": "MLB",
          "start_time": "2026-06-26T23:10Z",
          "tip": "Tampa Bay Rays Win",
          "units": 1
        },
        "probability": null,
        "source": "Scores24MLB",
        "source_url": "https://scores24.live/en/baseball/m-26-06-2026-tampa-bay-rays-arizona-diamondbacks-prediction",
        "sport": "MLB",
        "start_time": "2026-06-26T23:10Z",
        "tip": "Tampa Bay Rays Win",
        "units": 1
      },
      {
        "away_team": "New York Yankees",
        "date": "2026-06-26",
        "decision": "BET",
        "edge": null,
        "game": "New York Yankees @ Boston Red Sox",
        "home_team": "Boston Red Sox",
        "matchup": "New York Yankees @ Boston Red Sox",
        "odds": -161,
        "pick": "Total Under (9,5) (New York Yankees @ Boston Red Sox)",
        "pregame_snapshot": {
          "away_team": "New York Yankees",
          "date": "2026-06-26",
          "decision": "BET",
          "edge": null,
          "game": "New York Yankees @ Boston Red Sox",
          "home_team": "Boston Red Sox",
          "matchup": "New York Yankees @ Boston Red Sox",
          "odds": -161,
          "pick": "Total Under (9,5) (New York Yankees @ Boston Red Sox)",
          "probability": null,
          "source": "Scores24MLB",
          "source_url": "https://scores24.live/en/baseball/m-26-06-2026-boston-red-sox-new-york-yankees-prediction",
          "sport": "MLB",
          "start_time": "2026-06-26T23:10Z",
          "tip": "Total Under (9,5)",
          "units": 1
        },
        "probability": null,
        "source": "Scores24MLB",
        "source_url": "https://scores24.live/en/baseball/m-26-06-2026-boston-red-sox-new-york-yankees-prediction",
        "sport": "MLB",
        "start_time": "2026-06-26T23:10Z",
        "tip": "Total Under (9,5)",
        "units": 1
      },
      {
        "away_team": "Philadelphia Phillies",
        "date": "2026-06-26",
        "decision": "BET",
        "edge": null,
        "game": "Philadelphia Phillies @ New York Mets",
        "home_team": "New York Mets",
        "matchup": "Philadelphia Phillies @ New York Mets",
        "odds": -159,
        "pick": "Philadelphia Phillies ML (Philadelphia Phillies @ New York Mets)",
        "pregame_snapshot": {
          "away_team": "Philadelphia Phillies",
          "date": "2026-06-26",
          "decision": "BET",
          "edge": null,
          "game": "Philadelphia Phillies @ New York Mets",
          "home_team": "New York Mets",
          "matchup": "Philadelphia Phillies @ New York Mets",
          "odds": -159,
          "pick": "Philadelphia Phillies ML (Philadelphia Phillies @ New York Mets)",
          "probability": null,
          "source": "Scores24MLB",
          "source_url": "https://scores24.live/en/baseball/m-26-06-2026-new-york-mets-philadelphia-phillies-prediction",
          "sport": "MLB",
          "start_time": "2026-06-26T23:10Z",
          "tip": "Philadelphia Phillies Win",
          "units": 1
        },
        "probability": null,
        "source": "Scores24MLB",
        "source_url": "https://scores24.live/en/baseball/m-26-06-2026-new-york-mets-philadelphia-phillies-prediction",
        "sport": "MLB",
        "start_time": "2026-06-26T23:10Z",
        "tip": "Philadelphia Phillies Win",
        "units": 1
      },
      {
        "away_team": "Seattle Mariners",
        "date": "2026-06-26",
        "decision": "BET",
        "edge": null,
        "game": "Seattle Mariners @ Cleveland Guardians",
        "home_team": "Cleveland Guardians",
        "matchup": "Seattle Mariners @ Cleveland Guardians",
        "odds": -112,
        "pick": "Cleveland Gardians ML (Seattle Mariners @ Cleveland Guardians)",
        "pregame_snapshot": {
          "away_team": "Seattle Mariners",
          "date": "2026-06-26",
          "decision": "BET",
          "edge": null,
          "game": "Seattle Mariners @ Cleveland Guardians",
          "home_team": "Cleveland Guardians",
          "matchup": "Seattle Mariners @ Cleveland Guardians",
          "odds": -112,
          "pick": "Cleveland Gardians ML (Seattle Mariners @ Cleveland Guardians)",
          "probability": null,
          "source": "Scores24MLB",
          "source_url": "https://scores24.live/en/baseball/m-26-06-2026-cleveland-guardians-seattle-mariners-prediction",
          "sport": "MLB",
          "start_time": "2026-06-26T23:10Z",
          "tip": "Cleveland Gardians Win",
          "units": 1
        },
        "probability": null,
        "source": "Scores24MLB",
        "source_url": "https://scores24.live/en/baseball/m-26-06-2026-cleveland-guardians-seattle-mariners-prediction",
        "sport": "MLB",
        "start_time": "2026-06-26T23:10Z",
        "tip": "Cleveland Gardians Win",
        "units": 1
      },
      {
        "away_team": "Kansas City Royals",
        "date": "2026-06-26",
        "decision": "BET",
        "edge": null,
        "game": "Kansas City Royals @ Chicago White Sox",
        "home_team": "Chicago White Sox",
        "matchup": "Kansas City Royals @ Chicago White Sox",
        "odds": -137,
        "pick": "Total Over (7,5) (Kansas City Royals @ Chicago White Sox)",
        "pregame_snapshot": {
          "away_team": "Kansas City Royals",
          "date": "2026-06-26",
          "decision": "BET",
          "edge": null,
          "game": "Kansas City Royals @ Chicago White Sox",
          "home_team": "Chicago White Sox",
          "matchup": "Kansas City Royals @ Chicago White Sox",
          "odds": -137,
          "pick": "Total Over (7,5) (Kansas City Royals @ Chicago White Sox)",
          "probability": null,
          "source": "Scores24MLB",
          "source_url": "https://scores24.live/en/baseball/m-26-06-2026-chicago-white-sox-kansas-city-royals-prediction",
          "sport": "MLB",
          "start_time": "2026-06-26T23:40Z",
          "tip": "Total Over (7,5)",
          "units": 1
        },
        "probability": null,
        "source": "Scores24MLB",
        "source_url": "https://scores24.live/en/baseball/m-26-06-2026-chicago-white-sox-kansas-city-royals-prediction",
        "sport": "MLB",
        "start_time": "2026-06-26T23:40Z",
        "tip": "Total Over (7,5)",
        "units": 1
      },
      {
        "away_team": "Chicago Cubs",
        "date": "2026-06-26",
        "decision": "BET",
        "edge": null,
        "game": "Chicago Cubs @ Milwaukee Brewers",
        "home_team": "Milwaukee Brewers",
        "matchup": "Chicago Cubs @ Milwaukee Brewers",
        "odds": -189,
        "pick": "Total Over (6,5) (Chicago Cubs @ Milwaukee Brewers)",
        "pregame_snapshot": {
          "away_team": "Chicago Cubs",
          "date": "2026-06-26",
          "decision": "BET",
          "edge": null,
          "game": "Chicago Cubs @ Milwaukee Brewers",
          "home_team": "Milwaukee Brewers",
          "matchup": "Chicago Cubs @ Milwaukee Brewers",
          "odds": -189,
          "pick": "Total Over (6,5) (Chicago Cubs @ Milwaukee Brewers)",
          "probability": null,
          "source": "Scores24MLB",
          "source_url": "https://scores24.live/en/baseball/m-26-06-2026-milwaukee-brewers-chicago-cubs-prediction",
          "sport": "MLB",
          "start_time": "2026-06-26T23:45Z",
          "tip": "Total Over (6,5)",
          "units": 1
        },
        "probability": null,
        "source": "Scores24MLB",
        "source_url": "https://scores24.live/en/baseball/m-26-06-2026-milwaukee-brewers-chicago-cubs-prediction",
        "sport": "MLB",
        "start_time": "2026-06-26T23:45Z",
        "tip": "Total Over (6,5)",
        "units": 1
      },
      {
        "away_team": "Colorado Rockies",
        "date": "2026-06-26",
        "decision": "BET",
        "edge": null,
        "game": "Colorado Rockies @ Minnesota Twins",
        "home_team": "Minnesota Twins",
        "matchup": "Colorado Rockies @ Minnesota Twins",
        "odds": -141,
        "pick": "Total Over (8,5) (Colorado Rockies @ Minnesota Twins)",
        "pregame_snapshot": {
          "away_team": "Colorado Rockies",
          "date": "2026-06-26",
          "decision": "BET",
          "edge": null,
          "game": "Colorado Rockies @ Minnesota Twins",
          "home_team": "Minnesota Twins",
          "matchup": "Colorado Rockies @ Minnesota Twins",
          "odds": -141,
          "pick": "Total Over (8,5) (Colorado Rockies @ Minnesota Twins)",
          "probability": null,
          "source": "Scores24MLB",
          "source_url": "https://scores24.live/en/baseball/m-26-06-2026-minnesota-twins-colorado-rockies-prediction",
          "sport": "MLB",
          "start_time": "2026-06-27T00:10Z",
          "tip": "Total Over (8,5)",
          "units": 1
        },
        "probability": null,
        "source": "Scores24MLB",
        "source_url": "https://scores24.live/en/baseball/m-26-06-2026-minnesota-twins-colorado-rockies-prediction",
        "sport": "MLB",
        "start_time": "2026-06-27T00:10Z",
        "tip": "Total Over (8,5)",
        "units": 1
      },
      {
        "away_team": "Miami Marlins",
        "date": "2026-06-26",
        "decision": "BET",
        "edge": null,
        "game": "Miami Marlins @ St. Louis Cardinals",
        "home_team": "St. Louis Cardinals",
        "matchup": "Miami Marlins @ St. Louis Cardinals",
        "odds": 100,
        "pick": "Miami Marlins ML (Miami Marlins @ St. Louis Cardinals)",
        "pregame_snapshot": {
          "away_team": "Miami Marlins",
          "date": "2026-06-26",
          "decision": "BET",
          "edge": null,
          "game": "Miami Marlins @ St. Louis Cardinals",
          "home_team": "St. Louis Cardinals",
          "matchup": "Miami Marlins @ St. Louis Cardinals",
          "odds": 100,
          "pick": "Miami Marlins ML (Miami Marlins @ St. Louis Cardinals)",
          "probability": null,
          "source": "Scores24MLB",
          "source_url": "https://scores24.live/en/baseball/m-26-06-2026-st-louis-cardinals-miami-marlins-prediction",
          "sport": "MLB",
          "start_time": "2026-06-27T00:15Z",
          "tip": "Miami Marlins Win",
          "units": 1
        },
        "probability": null,
        "source": "Scores24MLB",
        "source_url": "https://scores24.live/en/baseball/m-26-06-2026-st-louis-cardinals-miami-marlins-prediction",
        "sport": "MLB",
        "start_time": "2026-06-27T00:15Z",
        "tip": "Miami Marlins Win",
        "units": 1
      },
      {
        "away_team": "Athletics",
        "date": "2026-06-26",
        "decision": "BET",
        "edge": null,
        "game": "Athletics @ Los Angeles Angels",
        "home_team": "Los Angeles Angels",
        "matchup": "Athletics @ Los Angeles Angels",
        "odds": -167,
        "pick": "Total Under (9,5) (Athletics @ Los Angeles Angels)",
        "pregame_snapshot": {
          "away_team": "Athletics",
          "date": "2026-06-26",
          "decision": "BET",
          "edge": null,
          "game": "Athletics @ Los Angeles Angels",
          "home_team": "Los Angeles Angels",
          "matchup": "Athletics @ Los Angeles Angels",
          "odds": -167,
          "pick": "Total Under (9,5) (Athletics @ Los Angeles Angels)",
          "probability": null,
          "source": "Scores24MLB",
          "source_url": "https://scores24.live/en/baseball/m-26-06-2026-los-angeles-angels-athletics-prediction",
          "sport": "MLB",
          "start_time": "2026-06-27T01:38Z",
          "tip": "Total Under (9,5)",
          "units": 1
        },
        "probability": null,
        "source": "Scores24MLB",
        "source_url": "https://scores24.live/en/baseball/m-26-06-2026-los-angeles-angels-athletics-prediction",
        "sport": "MLB",
        "start_time": "2026-06-27T01:38Z",
        "tip": "Total Under (9,5)",
        "units": 1
      },
      {
        "away_team": "Los Angeles Dodgers",
        "date": "2026-06-26",
        "decision": "BET",
        "edge": null,
        "game": "Los Angeles Dodgers @ San Diego Padres",
        "home_team": "San Diego Padres",
        "matchup": "Los Angeles Dodgers @ San Diego Padres",
        "odds": -222,
        "pick": "Total Under (9,5) (Los Angeles Dodgers @ San Diego Padres)",
        "pregame_snapshot": {
          "away_team": "Los Angeles Dodgers",
          "date": "2026-06-26",
          "decision": "BET",
          "edge": null,
          "game": "Los Angeles Dodgers @ San Diego Padres",
          "home_team": "San Diego Padres",
          "matchup": "Los Angeles Dodgers @ San Diego Padres",
          "odds": -222,
          "pick": "Total Under (9,5) (Los Angeles Dodgers @ San Diego Padres)",
          "probability": null,
          "source": "Scores24MLB",
          "source_url": "https://scores24.live/en/baseball/m-26-06-2026-san-diego-padres-los-angeles-dodgers-prediction",
          "sport": "MLB",
          "start_time": "2026-06-27T01:45Z",
          "tip": "Total Under (9,5)",
          "units": 1
        },
        "probability": null,
        "source": "Scores24MLB",
        "source_url": "https://scores24.live/en/baseball/m-26-06-2026-san-diego-padres-los-angeles-dodgers-prediction",
        "sport": "MLB",
        "start_time": "2026-06-27T01:45Z",
        "tip": "Total Under (9,5)",
        "units": 1
      }
    ],
    "updatedAt": "2026-06-26T13:04:04.811214Z"
  },
  "scores24_wnba": {
    "date": "2026-06-26",
    "generatedAt": "2026-06-26T13:04:04.811214Z",
    "generatedBy": "github-actions:external-feed-refresh",
    "meta": {
      "attemptedUrls": 3,
      "blockRetryRounds": 0,
      "blockedUrls": 0,
      "date": "2026-06-26",
      "expectedMatchups": 3,
      "feed": "scores24_wnba",
      "from": "github-actions",
      "leagues": "mlb,wnba,fifa_world_cup",
      "listingLinks": 11,
      "matchedPicks": 3,
      "missingMatchups": [],
      "officialMatchups": 3,
      "unpublishedMatchups": [],
      "updatedAt": "2026-06-26T13:04:04.811214Z"
    },
    "note": "Scores24WNBA matched 3 published editorial choice(s) against 3 official 2026-06-26 matchup(s).",
    "ok": true,
    "picks": [
      {
        "away_team": "Washington Mystics",
        "date": "2026-06-26",
        "decision": "BET",
        "edge": null,
        "game": "Washington Mystics @ Connecticut Sun",
        "home_team": "Connecticut Sun",
        "matchup": "Washington Mystics @ Connecticut Sun",
        "odds": -104,
        "pick": "Total points Under (162,5) (Washington Mystics @ Connecticut Sun)",
        "pregame_snapshot": {
          "away_team": "Washington Mystics",
          "date": "2026-06-26",
          "decision": "BET",
          "edge": null,
          "game": "Washington Mystics @ Connecticut Sun",
          "home_team": "Connecticut Sun",
          "matchup": "Washington Mystics @ Connecticut Sun",
          "odds": -104,
          "pick": "Total points Under (162,5) (Washington Mystics @ Connecticut Sun)",
          "probability": null,
          "source": "Scores24WNBA",
          "source_url": "https://scores24.live/en/basketball/m-26-06-2026-connecticut-sun-w-washington-mystics-w--prediction",
          "sport": "WNBA",
          "start_time": "2026-06-26T23:30Z",
          "tip": "Total points Under (162,5)",
          "units": 1
        },
        "probability": null,
        "source": "Scores24WNBA",
        "source_url": "https://scores24.live/en/basketball/m-26-06-2026-connecticut-sun-w-washington-mystics-w--prediction",
        "sport": "WNBA",
        "start_time": "2026-06-26T23:30Z",
        "tip": "Total points Under (162,5)",
        "units": 1
      },
      {
        "away_team": "Portland Fire",
        "date": "2026-06-26",
        "decision": "BET",
        "edge": null,
        "game": "Portland Fire @ Chicago Sky",
        "home_team": "Chicago Sky",
        "matchup": "Portland Fire @ Chicago Sky",
        "odds": -118,
        "pick": "Portland Fire (W) Total points Under (84,5) (Portland Fire @ Chicago Sky)",
        "pregame_snapshot": {
          "away_team": "Portland Fire",
          "date": "2026-06-26",
          "decision": "BET",
          "edge": null,
          "game": "Portland Fire @ Chicago Sky",
          "home_team": "Chicago Sky",
          "matchup": "Portland Fire @ Chicago Sky",
          "odds": -118,
          "pick": "Portland Fire (W) Total points Under (84,5) (Portland Fire @ Chicago Sky)",
          "probability": null,
          "source": "Scores24WNBA",
          "source_url": "https://scores24.live/en/basketball/m-26-06-2026-chicago-sky-w-portland-fire-prediction",
          "sport": "WNBA",
          "start_time": "2026-06-26T23:30Z",
          "tip": "Portland Fire (W) Total points Under (84,5)",
          "units": 1
        },
        "probability": null,
        "source": "Scores24WNBA",
        "source_url": "https://scores24.live/en/basketball/m-26-06-2026-chicago-sky-w-portland-fire-prediction",
        "sport": "WNBA",
        "start_time": "2026-06-26T23:30Z",
        "tip": "Portland Fire (W) Total points Under (84,5)",
        "units": 1
      },
      {
        "away_team": "Atlanta Dream",
        "date": "2026-06-26",
        "decision": "BET",
        "edge": null,
        "game": "Atlanta Dream @ Golden State Valkyries",
        "home_team": "Golden State Valkyries",
        "matchup": "Atlanta Dream @ Golden State Valkyries",
        "odds": -189,
        "pick": "Total points Over (156,5) (Atlanta Dream @ Golden State Valkyries)",
        "pregame_snapshot": {
          "away_team": "Atlanta Dream",
          "date": "2026-06-26",
          "decision": "BET",
          "edge": null,
          "game": "Atlanta Dream @ Golden State Valkyries",
          "home_team": "Golden State Valkyries",
          "matchup": "Atlanta Dream @ Golden State Valkyries",
          "odds": -189,
          "pick": "Total points Over (156,5) (Atlanta Dream @ Golden State Valkyries)",
          "probability": null,
          "source": "Scores24WNBA",
          "source_url": "https://scores24.live/en/basketball/m-27-06-2026-golden-state-valkyries-w-atlanta-dream-w--prediction",
          "sport": "WNBA",
          "start_time": "2026-06-27T02:00Z",
          "tip": "Total points Over (156,5)",
          "units": 1
        },
        "probability": null,
        "source": "Scores24WNBA",
        "source_url": "https://scores24.live/en/basketball/m-27-06-2026-golden-state-valkyries-w-atlanta-dream-w--prediction",
        "sport": "WNBA",
        "start_time": "2026-06-27T02:00Z",
        "tip": "Total points Over (156,5)",
        "units": 1
      }
    ],
    "updatedAt": "2026-06-26T13:04:04.811214Z"
  },
  "updatedAt": "2026-06-26T13:04:04.811214Z"
}
