{
  "as_of": "2026-05-15",
  "slate_date": "2026-05-15",
  "games": [
    {
      "away_team": "Philadelphia Phillies",
      "home_team": "Pittsburgh Pirates",
      "away_sp": "Aaron Nola",
      "home_sp": "Braxton Ashcraft",
      "cannon_away_xr": 4.57,
      "cannon_home_xr": 4.96,
      "cannon_total_xr": 9.53,
      "cannon_away_xwin": 0.4626,
      "cannon_home_xwin": 0.5374,
      "ml_pick_side": "home",
      "ml_pick_team": "Pittsburgh Pirates",
      "ml_fair_odds": -116,
      "ml_market_odds": 158,
      "ml_edge_pct": 0.3865,
      "total_line": 8.0,
      "total_pick_side": "over",
      "total_market_odds": -105,
      "total_edge_pct": 0.0738
    },
    {
      "away_team": "Baltimore Orioles",
      "home_team": "Washington Nationals",
      "away_sp": "Shane Baz",
      "home_sp": "Zack Littell",
      "cannon_away_xr": 5.42,
      "cannon_home_xr": 4.38,
      "cannon_total_xr": 9.8,
      "cannon_away_xwin": 0.5963,
      "cannon_home_xwin": 0.4037,
      "ml_pick_side": "away",
      "ml_pick_team": "Baltimore Orioles",
      "ml_fair_odds": -148,
      "ml_market_odds": -116,
      "ml_edge_pct": 0.1104,
      "total_line": 9.5,
      "total_pick_side": "over",
      "total_market_odds": -105,
      "total_edge_pct": 0.0738
    },
    {
      "away_team": "Toronto Blue Jays",
      "home_team": "Detroit Tigers",
      "away_sp": "Trey Yesavage",
      "home_sp": "Brenan Hanifee",
      "cannon_away_xr": 3.15,
      "cannon_home_xr": 3.67,
      "cannon_total_xr": 6.82,
      "cannon_away_xwin": 0.4306,
      "cannon_home_xwin": 0.5694,
      "ml_pick_side": "home",
      "ml_pick_team": "Detroit Tigers",
      "ml_fair_odds": -132,
      "ml_market_odds": 105,
      "ml_edge_pct": 0.1673,
      "total_line": 8.0,
      "total_pick_side": "under",
      "total_market_odds": 109,
      "total_edge_pct": 0.1495
    },
    {
      "away_team": "Cincinnati Reds",
      "home_team": "Cleveland Guardians",
      "away_sp": "Andrew Abbott",
      "home_sp": "Tanner Bibee",
      "cannon_away_xr": 4.21,
      "cannon_home_xr": 4.34,
      "cannon_total_xr": 8.55,
      "cannon_away_xwin": 0.4861,
      "cannon_home_xwin": 0.5139,
      "ml_pick_side": null,
      "ml_pick_team": null,
      "ml_fair_odds": null,
      "ml_market_odds": null,
      "ml_edge_pct": null,
      "total_line": 8.0,
      "total_pick_side": "over",
      "total_market_odds": -106,
      "total_edge_pct": 0.0689
    },
    {
      "away_team": "Miami Marlins",
      "home_team": "Tampa Bay Rays",
      "away_sp": "Janson Junk",
      "home_sp": "Jesse Scholtens",
      "cannon_away_xr": 4.27,
      "cannon_home_xr": 4.32,
      "cannon_total_xr": 8.59,
      "cannon_away_xwin": 0.4947,
      "cannon_home_xwin": 0.5053,
      "ml_pick_side": null,
      "ml_pick_team": null,
      "ml_fair_odds": null,
      "ml_market_odds": null,
      "ml_edge_pct": null,
      "total_line": 8.0,
      "total_pick_side": "over",
      "total_market_odds": 100,
      "total_edge_pct": 0.1
    },
    {
      "away_team": "Milwaukee Brewers",
      "home_team": "Minnesota Twins",
      "away_sp": "Jacob Misiorowski",
      "home_sp": "Joe Ryan",
      "cannon_away_xr": 4.49,
      "cannon_home_xr": 3.99,
      "cannon_total_xr": 8.48,
      "cannon_away_xwin": 0.5538,
      "cannon_home_xwin": 0.4462,
      "ml_pick_side": "away",
      "ml_pick_team": "Milwaukee Brewers",
      "ml_fair_odds": -124,
      "ml_market_odds": -107,
      "ml_edge_pct": 0.0714,
      "total_line": 8.5,
      "total_pick_side": "under",
      "total_market_odds": 120,
      "total_edge_pct": 0.21
    },
    {
      "away_team": "Boston Red Sox",
      "home_team": "Atlanta Braves",
      "away_sp": "Connelly Early",
      "home_sp": "Spencer Strider",
      "cannon_away_xr": 3.82,
      "cannon_home_xr": 4.15,
      "cannon_total_xr": 7.97,
      "cannon_away_xwin": 0.4622,
      "cannon_home_xwin": 0.5378,
      "ml_pick_side": null,
      "ml_pick_team": null,
      "ml_fair_odds": null,
      "ml_market_odds": null,
      "ml_edge_pct": null,
      "total_line": 7.5,
      "total_pick_side": "over",
      "total_market_odds": -117,
      "total_edge_pct": 0.0201
    },
    {
      "away_team": "New York Yankees",
      "home_team": "New York Mets",
      "away_sp": "Cam Schlittler",
      "home_sp": "Clay Holmes",
      "cannon_away_xr": 3.57,
      "cannon_home_xr": 2.91,
      "cannon_total_xr": 6.48,
      "cannon_away_xwin": 0.5924,
      "cannon_home_xwin": 0.4076,
      "ml_pick_side": null,
      "ml_pick_team": null,
      "ml_fair_odds": null,
      "ml_market_odds": null,
      "ml_edge_pct": null,
      "total_line": 7.0,
      "total_pick_side": "under",
      "total_market_odds": 104,
      "total_edge_pct": 0.122
    },
    {
      "away_team": "Chicago Cubs",
      "home_team": "Chicago White Sox",
      "away_sp": "Edward Cabrera",
      "home_sp": "Sean Burke",
      "cannon_away_xr": 5.18,
      "cannon_home_xr": 4.27,
      "cannon_total_xr": 9.45,
      "cannon_away_xwin": 0.5875,
      "cannon_home_xwin": 0.4125,
      "ml_pick_side": "away",
      "ml_pick_team": "Chicago Cubs",
      "ml_fair_odds": -142,
      "ml_market_odds": -135,
      "ml_edge_pct": 0.0227,
      "total_line": 8.5,
      "total_pick_side": "over",
      "total_market_odds": -106,
      "total_edge_pct": 0.0689
    },
    {
      "away_team": "Texas Rangers",
      "home_team": "Houston Astros",
      "away_sp": "Jack Leiter",
      "home_sp": "Spencer Arrighetti",
      "cannon_away_xr": 4.95,
      "cannon_home_xr": 4.62,
      "cannon_total_xr": 9.57,
      "cannon_away_xwin": 0.5315,
      "cannon_home_xwin": 0.4685,
      "ml_pick_side": "away",
      "ml_pick_team": "Texas Rangers",
      "ml_fair_odds": -113,
      "ml_market_odds": -112,
      "ml_edge_pct": 0.0061,
      "total_line": 8.5,
      "total_pick_side": "over",
      "total_market_odds": -112,
      "total_edge_pct": 0.0411
    },
    {
      "away_team": "Kansas City Royals",
      "home_team": "St. Louis Cardinals",
      "away_sp": "Michael Wacha",
      "home_sp": "Dustin May",
      "cannon_away_xr": 4.64,
      "cannon_home_xr": 4.34,
      "cannon_total_xr": 8.98,
      "cannon_away_xwin": 0.5305,
      "cannon_home_xwin": 0.4695,
      "ml_pick_side": "away",
      "ml_pick_team": "Kansas City Royals",
      "ml_fair_odds": -113,
      "ml_market_odds": -104,
      "ml_edge_pct": 0.0406,
      "total_line": 9.0,
      "total_pick_side": "under",
      "total_market_odds": 105,
      "total_edge_pct": 0.1275
    },
    {
      "away_team": "Arizona Diamondbacks",
      "home_team": "Colorado Rockies",
      "away_sp": "Merrill Kelly",
      "home_sp": "Kyle Freeland",
      "cannon_away_xr": 5.82,
      "cannon_home_xr": 5.82,
      "cannon_total_xr": 11.64,
      "cannon_away_xwin": 0.5,
      "cannon_home_xwin": 0.5,
      "ml_pick_side": null,
      "ml_pick_team": null,
      "ml_fair_odds": null,
      "ml_market_odds": null,
      "ml_edge_pct": null,
      "total_line": 11.0,
      "total_pick_side": "over",
      "total_market_odds": -115,
      "total_edge_pct": 0.0283
    },
    {
      "away_team": "Los Angeles Dodgers",
      "home_team": "Los Angeles Angels",
      "away_sp": "Blake Snell",
      "home_sp": "Jack Kochanowicz",
      "cannon_away_xr": 6.35,
      "cannon_home_xr": 3.52,
      "cannon_total_xr": 9.87,
      "cannon_away_xwin": 0.7464,
      "cannon_home_xwin": 0.2536,
      "ml_pick_side": "away",
      "ml_pick_team": "Los Angeles Dodgers",
      "ml_fair_odds": -294,
      "ml_market_odds": -224,
      "ml_edge_pct": 0.0796,
      "total_line": 9.0,
      "total_pick_side": "over",
      "total_market_odds": -110,
      "total_edge_pct": 0.05
    },
    {
      "away_team": "San Diego Padres",
      "home_team": "Seattle Mariners",
      "away_sp": "Randy Vasquez",
      "home_sp": "Emerson Hancock",
      "cannon_away_xr": 3.69,
      "cannon_home_xr": 4.68,
      "cannon_total_xr": 8.37,
      "cannon_away_xwin": 0.3929,
      "cannon_home_xwin": 0.6071,
      "ml_pick_side": "home",
      "ml_pick_team": "Seattle Mariners",
      "ml_fair_odds": -155,
      "ml_market_odds": -132,
      "ml_edge_pct": 0.067,
      "total_line": 7.0,
      "total_pick_side": "over",
      "total_market_odds": -116,
      "total_edge_pct": 0.0241
    },
    {
      "away_team": "San Francisco Giants",
      "home_team": "Athletics",
      "away_sp": "Tyler Mahle",
      "home_sp": "Aaron Civale",
      "cannon_away_xr": 4.97,
      "cannon_home_xr": 5.31,
      "cannon_total_xr": 10.28,
      "cannon_away_xwin": 0.4698,
      "cannon_home_xwin": 0.5302,
      "ml_pick_side": null,
      "ml_pick_team": null,
      "ml_fair_odds": null,
      "ml_market_odds": null,
      "ml_edge_pct": null,
      "total_line": 10.0,
      "total_pick_side": "over",
      "total_market_odds": -105,
      "total_edge_pct": 0.0738
    }
  ],
  "picks": [
    {
      "source": "Cannon Analytics",
      "pick": "Pittsburgh Pirates ML (Philadelphia Phillies vs Pittsburgh Pirates)",
      "matchup": "Philadelphia Phillies vs Pittsburgh Pirates",
      "sport": "MLB",
      "odds": 158,
      "probability": 0.5374,
      "edge": 38.6,
      "model_prediction": null,
      "kelly_pct": 5.0,
      "decision": "BET",
      "away_team": "Philadelphia Phillies",
      "home_team": "Pittsburgh Pirates"
    },
    {
      "source": "Cannon Analytics",
      "pick": "Over 8.0 (Philadelphia Phillies vs Pittsburgh Pirates)",
      "matchup": "Philadelphia Phillies vs Pittsburgh Pirates",
      "sport": "MLB",
      "odds": -105,
      "probability": 0.55,
      "edge": 7.4,
      "model_prediction": 9.53,
      "kelly_pct": 1.94,
      "decision": "BET",
      "away_team": "Philadelphia Phillies",
      "home_team": "Pittsburgh Pirates"
    },
    {
      "source": "Cannon Analytics",
      "pick": "Baltimore Orioles ML (Baltimore Orioles vs Washington Nationals)",
      "matchup": "Baltimore Orioles vs Washington Nationals",
      "sport": "MLB",
      "odds": -116,
      "probability": 0.5963,
      "edge": 11.0,
      "model_prediction": null,
      "kelly_pct": 3.2,
      "decision": "BET",
      "away_team": "Baltimore Orioles",
      "home_team": "Washington Nationals"
    },
    {
      "source": "Cannon Analytics",
      "pick": "Over 9.5 (Baltimore Orioles vs Washington Nationals)",
      "matchup": "Baltimore Orioles vs Washington Nationals",
      "sport": "MLB",
      "odds": -105,
      "probability": 0.55,
      "edge": 7.4,
      "model_prediction": 9.8,
      "kelly_pct": 1.94,
      "decision": "BET",
      "away_team": "Baltimore Orioles",
      "home_team": "Washington Nationals"
    },
    {
      "source": "Cannon Analytics",
      "pick": "Detroit Tigers ML (Toronto Blue Jays vs Detroit Tigers)",
      "matchup": "Toronto Blue Jays vs Detroit Tigers",
      "sport": "MLB",
      "odds": 105,
      "probability": 0.5694,
      "edge": 16.7,
      "model_prediction": null,
      "kelly_pct": 3.98,
      "decision": "BET",
      "away_team": "Toronto Blue Jays",
      "home_team": "Detroit Tigers"
    },
    {
      "source": "Cannon Analytics",
      "pick": "Under 8.0 (Toronto Blue Jays vs Detroit Tigers)",
      "matchup": "Toronto Blue Jays vs Detroit Tigers",
      "sport": "MLB",
      "odds": 109,
      "probability": 0.55,
      "edge": 14.9,
      "model_prediction": 6.82,
      "kelly_pct": 3.43,
      "decision": "BET",
      "away_team": "Toronto Blue Jays",
      "home_team": "Detroit Tigers"
    },
    {
      "source": "Cannon Analytics",
      "pick": "Over 8.0 (Cincinnati Reds vs Cleveland Guardians)",
      "matchup": "Cincinnati Reds vs Cleveland Guardians",
      "sport": "MLB",
      "odds": -106,
      "probability": 0.55,
      "edge": 6.9,
      "model_prediction": 8.55,
      "kelly_pct": 1.83,
      "decision": "BET",
      "away_team": "Cincinnati Reds",
      "home_team": "Cleveland Guardians"
    },
    {
      "source": "Cannon Analytics",
      "pick": "Over 8.0 (Miami Marlins vs Tampa Bay Rays)",
      "matchup": "Miami Marlins vs Tampa Bay Rays",
      "sport": "MLB",
      "odds": 100,
      "probability": 0.55,
      "edge": 10.0,
      "model_prediction": 8.59,
      "kelly_pct": 2.5,
      "decision": "BET",
      "away_team": "Miami Marlins",
      "home_team": "Tampa Bay Rays"
    },
    {
      "source": "Cannon Analytics",
      "pick": "Milwaukee Brewers ML (Milwaukee Brewers vs Minnesota Twins)",
      "matchup": "Milwaukee Brewers vs Minnesota Twins",
      "sport": "MLB",
      "odds": -107,
      "probability": 0.5538,
      "edge": 7.1,
      "model_prediction": null,
      "kelly_pct": 1.91,
      "decision": "BET",
      "away_team": "Milwaukee Brewers",
      "home_team": "Minnesota Twins"
    },
    {
      "source": "Cannon Analytics",
      "pick": "Under 8.5 (Milwaukee Brewers vs Minnesota Twins)",
      "matchup": "Milwaukee Brewers vs Minnesota Twins",
      "sport": "MLB",
      "odds": 120,
      "probability": 0.55,
      "edge": 21.0,
      "model_prediction": 8.48,
      "kelly_pct": 4.38,
      "decision": "BET",
      "away_team": "Milwaukee Brewers",
      "home_team": "Minnesota Twins"
    },
    {
      "source": "Cannon Analytics",
      "pick": "Over 7.5 (Boston Red Sox vs Atlanta Braves)",
      "matchup": "Boston Red Sox vs Atlanta Braves",
      "sport": "MLB",
      "odds": -117,
      "probability": 0.55,
      "edge": 2.0,
      "model_prediction": 7.97,
      "kelly_pct": 0.59,
      "decision": "PASS",
      "away_team": "Boston Red Sox",
      "home_team": "Atlanta Braves"
    },
    {
      "source": "Cannon Analytics",
      "pick": "Under 7.0 (New York Yankees vs New York Mets)",
      "matchup": "New York Yankees vs New York Mets",
      "sport": "MLB",
      "odds": 104,
      "probability": 0.55,
      "edge": 12.2,
      "model_prediction": 6.48,
      "kelly_pct": 2.93,
      "decision": "BET",
      "away_team": "New York Yankees",
      "home_team": "New York Mets"
    },
    {
      "source": "Cannon Analytics",
      "pick": "Chicago Cubs ML (Chicago Cubs vs Chicago White Sox)",
      "matchup": "Chicago Cubs vs Chicago White Sox",
      "sport": "MLB",
      "odds": -135,
      "probability": 0.5875,
      "edge": 2.3,
      "model_prediction": null,
      "kelly_pct": 0.77,
      "decision": "PASS",
      "away_team": "Chicago Cubs",
      "home_team": "Chicago White Sox"
    },
    {
      "source": "Cannon Analytics",
      "pick": "Over 8.5 (Chicago Cubs vs Chicago White Sox)",
      "matchup": "Chicago Cubs vs Chicago White Sox",
      "sport": "MLB",
      "odds": -106,
      "probability": 0.55,
      "edge": 6.9,
      "model_prediction": 9.45,
      "kelly_pct": 1.83,
      "decision": "BET",
      "away_team": "Chicago Cubs",
      "home_team": "Chicago White Sox"
    },
    {
      "source": "Cannon Analytics",
      "pick": "Texas Rangers ML (Texas Rangers vs Houston Astros)",
      "matchup": "Texas Rangers vs Houston Astros",
      "sport": "MLB",
      "odds": -112,
      "probability": 0.5315,
      "edge": 0.6,
      "model_prediction": null,
      "kelly_pct": 0.17,
      "decision": "PASS",
      "away_team": "Texas Rangers",
      "home_team": "Houston Astros"
    },
    {
      "source": "Cannon Analytics",
      "pick": "Over 8.5 (Texas Rangers vs Houston Astros)",
      "matchup": "Texas Rangers vs Houston Astros",
      "sport": "MLB",
      "odds": -112,
      "probability": 0.55,
      "edge": 4.1,
      "model_prediction": 9.57,
      "kelly_pct": 1.15,
      "decision": "LEAN",
      "away_team": "Texas Rangers",
      "home_team": "Houston Astros"
    },
    {
      "source": "Cannon Analytics",
      "pick": "Kansas City Royals ML (Kansas City Royals vs St. Louis Cardinals)",
      "matchup": "Kansas City Royals vs St. Louis Cardinals",
      "sport": "MLB",
      "odds": -104,
      "probability": 0.5305,
      "edge": 4.1,
      "model_prediction": null,
      "kelly_pct": 1.06,
      "decision": "LEAN",
      "away_team": "Kansas City Royals",
      "home_team": "St. Louis Cardinals"
    },
    {
      "source": "Cannon Analytics",
      "pick": "Under 9.0 (Kansas City Royals vs St. Louis Cardinals)",
      "matchup": "Kansas City Royals vs St. Louis Cardinals",
      "sport": "MLB",
      "odds": 105,
      "probability": 0.55,
      "edge": 12.8,
      "model_prediction": 8.98,
      "kelly_pct": 3.04,
      "decision": "BET",
      "away_team": "Kansas City Royals",
      "home_team": "St. Louis Cardinals"
    },
    {
      "source": "Cannon Analytics",
      "pick": "Over 11.0 (Arizona Diamondbacks vs Colorado Rockies)",
      "matchup": "Arizona Diamondbacks vs Colorado Rockies",
      "sport": "MLB",
      "odds": -115,
      "probability": 0.55,
      "edge": 2.8,
      "model_prediction": 11.64,
      "kelly_pct": 0.81,
      "decision": "PASS",
      "away_team": "Arizona Diamondbacks",
      "home_team": "Colorado Rockies"
    },
    {
      "source": "Cannon Analytics",
      "pick": "Los Angeles Dodgers ML (Los Angeles Dodgers vs Los Angeles Angels)",
      "matchup": "Los Angeles Dodgers vs Los Angeles Angels",
      "sport": "MLB",
      "odds": -224,
      "probability": 0.7464,
      "edge": 8.0,
      "model_prediction": null,
      "kelly_pct": 4.46,
      "decision": "BET",
      "away_team": "Los Angeles Dodgers",
      "home_team": "Los Angeles Angels"
    },
    {
      "source": "Cannon Analytics",
      "pick": "Over 9.0 (Los Angeles Dodgers vs Los Angeles Angels)",
      "matchup": "Los Angeles Dodgers vs Los Angeles Angels",
      "sport": "MLB",
      "odds": -110,
      "probability": 0.55,
      "edge": 5.0,
      "model_prediction": 9.87,
      "kelly_pct": 1.38,
      "decision": "BET",
      "away_team": "Los Angeles Dodgers",
      "home_team": "Los Angeles Angels"
    },
    {
      "source": "Cannon Analytics",
      "pick": "Seattle Mariners ML (San Diego Padres vs Seattle Mariners)",
      "matchup": "San Diego Padres vs Seattle Mariners",
      "sport": "MLB",
      "odds": -132,
      "probability": 0.6071,
      "edge": 6.7,
      "model_prediction": null,
      "kelly_pct": 2.21,
      "decision": "BET",
      "away_team": "San Diego Padres",
      "home_team": "Seattle Mariners"
    },
    {
      "source": "Cannon Analytics",
      "pick": "Over 7.0 (San Diego Padres vs Seattle Mariners)",
      "matchup": "San Diego Padres vs Seattle Mariners",
      "sport": "MLB",
      "odds": -116,
      "probability": 0.55,
      "edge": 2.4,
      "model_prediction": 8.37,
      "kelly_pct": 0.7,
      "decision": "PASS",
      "away_team": "San Diego Padres",
      "home_team": "Seattle Mariners"
    },
    {
      "source": "Cannon Analytics",
      "pick": "Over 10.0 (San Francisco Giants vs Athletics)",
      "matchup": "San Francisco Giants vs Athletics",
      "sport": "MLB",
      "odds": -105,
      "probability": 0.55,
      "edge": 7.4,
      "model_prediction": 10.28,
      "kelly_pct": 1.94,
      "decision": "BET",
      "away_team": "San Francisco Giants",
      "home_team": "Athletics"
    }
  ]
}